Workbook
Name Slicer_Category: #N/A
Name Slicer_Department: #N/A
Name Slicer_Month: #N/A
Name Slicer_Quarter: #N/A
Name Slicer_Region: #N/A
Name Slicer_Sub_Category: #N/A
Name Slicer_Year: #N/A

Sheet Raw_Data
A1: Transaction ID | B1: Date | C1: Month | D1: Quarter | E1: Year | F1: Region | G1: Country | H1: State | I1: City | J1: Branch | K1: Department | L1: Cost Center | M1: Product ID | N1: Product Name | O1: Category | P1: Sub Category | Q1: Revenue | R1: Budget Revenue | S1: COGS | T1: Operating Expense | U1: Marketing Expense | V1: Salary Expense | W1: Misc Expense | X1: Total Expense | Y1: Gross Profit | Z1: Net Profit | AA1: Profit Margin % | AB1: Budget Variance | AC1: Discount | AD1: Tax | AE1: Net Revenue
A2: TXN-00001 | B2: 45850 | C2: July | D2: Q3 | E2: 2025 | F2: West | G2: India | H2: Goa | I2: Vasco da Gama | J2: Branch D | K2: Operations | L2: CC-1002 | M2: P019 | N2: Conference Camera | O2: Electronics | P2: Video Conferencing | Q2: 23278.76 | R2: 22815.81 | S2: 11971.99 | T2: 2376.09 | U2: 667.33 | V2: 2275.73 | W2: 997.48 | X2: 18288.61 | Y2: 11306.77 | Z2: -6981.84 | AA2: -0.2542 | AB2: 462.95 | AC2: 0 | AD2: 4190.18 | AE2: 27468.94
A3: TXN-00002 | B3: 45908 | C3: September | D3: Q3 | E3: 2025 | F3: South | G3: India | H3: Tamil Nadu | I3: Chennai | J3: Branch D | K3: Sales | L3: CC-1003 | M3: P010 | N3: Mouse | O3: Accessories | P3: Computer Accessories | Q3: 2086.76 | R3: 1982.07 | S3: 1047.02 | T3: 207.57 | U3: 104.05 | V3: 247.61 | W3: 54.96 | X3: 1661.21 | Y3: 1039.74 | Z3: -621.47 | AA3: -0.2743 | AB3: 104.69 | AC3: 166.94 | AD3: 345.57 | AE3: 2265.39
A4: TXN-00003 | B4: 46076 | C4: February | D4: Q1 | E4: 2026 | F4: North | G4: India | H4: Uttar Pradesh | I4: Lucknow | J4: Branch D | K4: Operations | L4: CC-1002 | M4: P009 | N4: Keyboard | O4: Accessories | P4: Computer Accessories | Q4: 1176.9 | R4: 1120.77 | S4: 757.9 | T4: 116.28 | U4: 93.16 | V4: 63.4 | W4: 27.88 | X4: 1058.62 | Y4: 419 | Z4: -639.62 | AA4: -0.47 | AB4: 56.13 | AC4: 23.54 | AD4: 207.6 | AE4: 1360.97
A5: TXN-00004 | B5: 45801 | C5: May | D5: Q2 | E5: 2025 | F5: East | G5: India | H5: Odisha | I5: Bhubaneswar | J5: Branch C | K5: Marketing | L5: CC-1004 | M5: P002 | N5: Monitor | O5: Electronics | P5: Computing | Q5: 47762.94 | R5: 52452.38 | S5: 26669.38 | T5: 4567.83 | U5: 2811.05 | V5: 5583.19 | W5: 1889.44 | X5: 41520.9 | Y5: 21093.56 | Z5: -20427.34 | AA5: -0.402 | AB5: -4689.44 | AC5: 2388.15 | AD5: 5444.98 | AE5: 50819.77
A6: TXN-00005 | B6: 46027 | C6: January | D6: Q1 | E6: 2026 | F6: South | G6: India | H6: Kerala | I6: Kochi | J6: Branch A | K6: Sales | L6: CC-1005 | M6: P001 | N6: Business Laptop | O6: Electronics | P6: Computing | Q6: 18810.62 | R6: 18781.73 | S6: 10354.06 | T6: 961.72 | U6: 713.39 | V6: 1822.89 | W6: 708.34 | X6: 14560.39 | Y6: 8456.55 | Z6: -6103.84 | AA6: -0.2895 | AB6: 28.88 | AC6: 940.53 | AD6: 3216.62 | AE6: 21086.7
A7: TXN-00006 | B7: 45788 | C7: May | D7: Q2 | E7: 2025 | F7: Central | G7: India | H7: Madhya Pradesh | I7: Indore | J7: Branch A | K7: Sales | L7: CC-1005 | M7: P003 | N7: Printer | O7: Electronics | P7: Office Equipment | Q7: 41891.12 | R7: 43917.52 | S7: 23957.63 | T7: 5351.04 | U7: 3358.8 | V7: 4094.37 | W7: 764.91 | X7: 37526.76 | Y7: 17933.48 | Z7: -19593.28 | AA7: -0.4545 | AB7: -2026.4 | AC7: 837.82 | AD7: 2052.66 | AE7: 43105.96
A8: TXN-00007 | B8: 45954 | C8: October | D8: Q4 | E8: 2025 | F8: East | G8: India | H8: Odisha | I8: Bhubaneswar | J8: Branch C | K8: Sales | L8: CC-1001 | M8: P020 | N8: Document Scanner | O8: Electronics | P8: Office Equipment | Q8: 51914.87 | R8: 47855.1 | S8: 32449.92 | T8: 4837.81 | U8: 1983.1 | V8: 5992.44 | W8: 1607.3 | X8: 46870.57 | Y8: 19464.95 | Z8: -27405.61 | AA8: -0.4709 | AB8: 4059.77 | AC8: 2595.74 | AD8: 8877.44 | AE8: 58196.57
A9: TXN-00008 | B9: 45917 | C9: September | D9: Q3 | E9: 2025 | F9: West | G9: India | H9: Maharashtra | I9: Mumbai | J9: Branch B | K9: Finance | L9: CC-1004 | M9: P012 | N9: Accounting Software | O9: Software | P9: Business Software | Q9: 18661.59 | R9: 18238.04 | S9: 9504.37 | T9: 1465.01 | U9: 1566.53 | V9: 1152.74 | W9: 609.66 | X9: 14298.29 | Y9: 9157.22 | Z9: -5141.07 | AA9: -0.246 | AB9: 423.55 | AC9: 0 | AD9: 2239.39 | AE9: 20900.98
A10: TXN-00009 | B10: 46006 | C10: December | D10: Q4 | E10: 2025 | F10: North | G10: India | H10: Uttar Pradesh | I10: Agra | J10: Branch A | K10: Finance | L10: CC-1001 | M10: P019 | N10: Conference Camera | O10: Electronics | P10: Video Conferencing | Q10: 27488.07 | R10: 25577.3 | S10: 14637.49 | T10: 2601.69 | U10: 1408.75 | V10: 1242.22 | W10: 519.17 | X10: 20409.32 | Y10: 12850.58 | Z10: -7558.74 | AA10: -0.2378 | AB10: 1910.77 | AC10: 549.76 | AD10: 4848.89 | AE10: 31787.2
A11: TXN-00010 | B11: 45860 | C11: July | D11: Q3 | E11: 2025 | F11: North | G11: India | H11: Uttar Pradesh | I11: Lucknow | J11: Branch C | K11: Operations | L11: CC-1002 | M11: P005 | N11: Office Desk | O11: Furniture | P11: Office Furniture | Q11: 17627.99 | R11: 19112.48 | S11: 10707.67 | T11: 1512.88 | U11: 1074.22 | V11: 1540.96 | W11: 226.16 | X11: 15061.9 | Y11: 6920.32 | Z11: -8141.58 | AA11: -0.4535 | AB11: -1484.48 | AC11: 528.84 | AD11: 854.96 | AE11: 17954.11
A12: TXN-00011 | B12: 46041 | C12: January | D12: Q1 | E12: 2026 | F12: South | G12: India | H12: Kerala | I12: Thiruvananthapuram | J12: Branch B | K12: Finance | L12: CC-1001 | M12: P009 | N12: Keyboard | O12: Accessories | P12: Computer Accessories | Q12: 3190.87 | R12: 2847 | S12: 1984.13 | T12: 332.5 | U12: 83.21 | V12: 258.36 | W12: 57.2 | X12: 2715.4 | Y12: 1206.74 | Z12: -1508.66 | AA12: -0.474 | AB12: 343.87 | AC12: 159.54 | AD12: 151.57 | AE12: 3182.89
A13: TXN-00012 | B13: 45875 | C13: August | D13: Q3 | E13: 2025 | F13: East | G13: India | H13: Jharkhand | I13: Ranchi | J13: Branch C | K13: Sales | L13: CC-1001 | M13: P018 | N13: Projector | O13: Electronics | P13: Presentation | Q13: 78448.53 | R13: 75105.25 | S13: 50081.24 | T13: 9051.22 | U13: 4792.27 | V13: 6461.97 | W13: 1448.54 | X13: 71835.23 | Y13: 28367.29 | Z13: -43467.94 | AA13: -0.4696 | AB13: 3343.28 | AC13: 0 | AD13: 14120.74 | AE13: 92569.27
... A206: TXN-00205 | B206: 45776 | C206: April | D206: Q2 | E206: 2025 | F206: West | G206: India | H206: Rajasthan | I206: Jodhpur | J206: Branch D | K206: IT | L206: CC-1004 | M206: P009 | N206: Keyboard | O206: Accessories | P206: Computer Accessories | Q206: 6731.64 | R206: 7582.63 | S206: 4593.66 | T206: 597.82 | U206: 314.27 | V206: 695.54 | W206: 173.64 | X206: 6374.94 | Y206: 2137.98 | Z206: -4236.96 | AA206: -0.5443 | AB206: -850.99 | AC206: 134.63 | AD206: 1187.46 | AE206: 7784.46
A207: TXN-00206 | B207: 46018 | C207: December | D207: Q4 | E207: 2025 | F207: East | G207: India | H207: West Bengal | J207: Branch B | K207: Operations | L207: CC-1002 | M207: P019 | N207: Conference Camera | O207: Electronics | P207: Video Conferencing | Q207: 27294.21 | R207: 24362.7 | S207: 16240.67 | T207: 1761.51 | U207: 2000.67 | V207: 2943.25 | W207: 794.14 | X207: 23740.24 | Y207: 11053.54 | Z207: -12686.7 | AA207: -0.4611 | AB207: 2931.52 | AC207: 2729.42 | AD207: 2947.78 | AE207: 27512.57
A208: TXN-00207 | B208: 46080 | C208: February | D208: Q1 | E208: 2026 | F208: West | G208: India | H208: Goa | I208: Panaji | J208: Branch C | K208: Sales | L208: CC-1003 | M208: P019 | N208: Conference Camera | O208: Electronics | P208: Video Conferencing | Q208: 25282.94 | R208: 26863.7 | S208: 16423.6 | T208: 2021.58 | U208: 1239.28 | V208: 1102.98 | W208: 562.5 | X208: 21349.94 | Y208: 8859.34 | Z208: -12490.6 | AA208: -0.4795 | AB208: -1580.76 | AC208: 2022.64 | AD208: 2791.24 | AE208: 26051.54
A209: TXN-00208 | B209: 45809 | C209: June | D209: Q2 | E209: 2025 | F209: West | G209: India | H209: Maharashtra | I209: Nagpur | J209: Branch D | K209: Sales | L209: CC-1001 | M209: P004 | N209: Office Chair | O209: Furniture | P209: Office Furniture | Q209: 27355.34 | R209: 30489.93 | S209: 18065.99 | T209: 3125.08 | U209: 1604.95 | V209: 1401.3 | W209: 916.14 | X209: 25113.47 | Y209: 9289.35 | Z209: -15824.12 | AA209: -0.516 | AB209: -3134.59 | AC209: 1367.77 | AD209: 4677.76 | AE209: 30665.33
A210: TXN-00209 | B210: 45818 | C210: June | D210: Q2 | E210: 2025 | F210: West | G210: India | H210: Goa | I210: Margao | J210: Branch A | K210: Sales | L210: CC-1003 | M210: P004 | N210: Office Chair | O210: Furniture | P210: Office Furniture | Q210: 28763.31 | R210: 31854.79 | S210: 15925.01 | T210: 2393.04 | U210: 2051.7 | V210: 2039.23 | W210: 880.09 | X210: 23289.08 | Y210: 12838.3 | Z210: -10450.78 | AA210: -0.331 | AB210: -3091.49 | AC210: 575.27 | AD210: 3382.57 | AE210: 31570.61
A211: TXN-00210 | B211: 45841 | C211: July | D211: Q3 | E211: 2025 | F211: Central | G211: India | H211: Chhattisgarh | I211: Bilaspur | J211: Branch C | K211: Operations | L211: CC-1002 | M211: P002 | N211: Monitor | O211: Electronics | P211: Computing | Q211: 24677.74 | R211: 25053.66 | S211: 17522.17 | T211: 2084.95 | U211: 1498.12 | V211: 2039.87 | W211: 796.76 | X211: 23941.87 | Y211: 7155.57 | Z211: -16786.29 | AA211: -0.6819 | AB211: -375.91 | AC211: 1233.89 | AD211: 1172.19 | AE211: 24616.05
A212: TXN-00211 | B212: 45920 | C212: September | D212: Q3 | E212: 2025 | F212: West | G212: India | H212: Maharashtra | I212: Pune | J212: Branch B | K212: Sales | L212: CC-1004 | M212: P007 | N212: Tablet | O212: Electronics | P212: Mobile | Q212: 34917.73 | R212: 39264.36 | S212: 23280.56 | T212: 3871.26 | U212: 1299.01 | V212: 1643.61 | W212: 1203.38 | X212: 31297.81 | Y212: 11637.17 | Z212: -19660.64 | AA212: -0.5183 | AB212: -4346.63 | AC212: 1047.53 | AD212: 4064.42 | AE212: 37934.62
A213: TXN-00212 | B213: 46004 | C213: December | D213: Q4 | E213: 2025 | F213: East | G213: India | H213: Odisha | I213: Cuttack | J213: Branch A | K213: Marketing | L213: CC-1003 | M213: P015 | N213: Network Router | O213: Networking | P213: Network Equipment | Q213: 17482.77 | R213: 18882.34 | S213: 9747.11 | T213: 2129.99 | U213: 1446.31 | V213: 1154.27 | W213: 726.12 | X213: 15203.8 | Y213: 7735.66 | Z213: -7468.14 | AA213: -0.4022 | AB213: -1399.57 | AC213: 1748.28 | AD213: 2832.21 | AE213: 18566.7
A214: TXN-00213 | B214: 46005 | C214: December | D214: Q4 | E214: 2025 | F214: West | G214: India | H214: Maharashtra | I214: Pune | J214: Branch A | K214: Sales | L214: CC-1003 | M214: P020 | N214: Document Scanner | O214: Electronics | P214: Office Equipment | Q214: 79192.1 | R214: 88727.18 | S214: 50827.24 | T214: 3995.83 | U214: 4377.63 | V214: 6786.21 | W214: 1634.61 | X214: 67621.53 | Y214: 28364.86 | Z214: -39256.67 | AA214: -0.4287 | AB214: -9535.08 | AC214: 1583.84 | AD214: 13969.49 | AE214: 91577.75
A215: TXN-00214 | B215: 45934 | C215: October | D215: Q4 | E215: 2025 | F215: West | G215: India | H215: Gujarat | I215: Vadodara | J215: Branch B | K215: Sales | L215: CC-1005 | M215: P003 | N215: Printer | O215: Electronics | P215: Office Equipment | Q215: 14247.77 | R215: 16455.9 | S215: 9253.61 | T215: 1064.54 | U215: 479.04 | V215: 1153.08 | W215: 145.14 | X215: 12095.42 | Y215: 4994.16 | Z215: -7101.27 | AA215: -0.4945 | AB215: -2208.13 | AC215: 1424.78 | AD215: 1538.76 | AE215: 14361.75
A216: TXN-00215 | B216: 45872 | C216: August | D216: Q3 | E216: 2025 | F216: West | G216: India | H216: Maharashtra | I216: Mumbai | J216: Branch A | K216: Marketing | L216: CC-1003 | M216: P002 | N216: Monitor | O216: Electronics | P216: Computing | Q216: 50404.03 | R216: 47816.42 | S216: 31414.03 | T216: 6262.93 | U216: 4304.21 | V216: 3394.83 | W216: 1434.94 | X216: 46810.94 | Y216: 18990 | Z216: -27820.94 | AA216: -0.4773 | AB216: 2587.61 | AC216: 1008.08 | AD216: 8891.27 | AE216: 58287.23
A217: TXN-00216 | B217: 46015 | C217: December | D217: Q4 | E217: 2025 | F217: East | G217: India | H217: Odisha | I217: Bhubaneswar | J217: Branch B | K217: Marketing | L217: CC-1001 | M217: P014 | N217: Data Storage | O217: Software | P217: Cloud Services | Q217: 6369.34 | R217: 6894.41 | S217: 4092.99 | T217: 508.59 | U217: 549.1 | V217: 340.05 | W217: 175.24 | X217: 5665.97 | Y217: 2276.36 | Z217: -3389.61 | AA217: -0.4747 | AB217: -525.06 | AC217: 318.47 | AD217: 1089.16 | AE217: 7140.04
A218: TXN-00217 | B218: 45929 | C218: September | D218: Q3 | E218: 2025 | F218: South | G218: India | H218: Telangana | I218: Hyderabad | J218: Branch D | K218: Marketing | L218: CC-1001 | M218: P015 | N218: Network Router | O218: Networking | P218: Network Equipment | Q218: 9860.57 | R218: 10392.23 | S218: 5804.9 | T218: 1241.44 | U218: 285.36 | V218: 935.09 | W218: 107.22 | X218: 8374.02 | Y218: 4055.67 | Z218: -4318.35 | AA218: -0.391 | AB218: -531.66 | AC218: 0 | AD218: 1183.27 | AE218: 11043.84
A219: TXN-00218 | B219: 46043 | C219: January | D219: Q1 | E219: 2026 | F219: West | G219: India | H219: Gujarat | I219: Surat | J219: Branch C | K219: Operations | L219: CC-1002 | M219: P013 | N219: CRM Software | O219: Software | P219: Business Software | Q219: 9333.46 | R219: 8989.09 | S219: 6543.81 | T219: 902.13 | U219: 593 | V219: 638.35 | W219: 110.32 | X219: 8787.61 | Y219: 2789.64 | Z219: -5997.97 | AA219: -0.5738 | AB219: 344.37 | AC219: 0 | AD219: 1120.01 | AE219: 10453.47
... A1001: TXN-01000 | B1001: 46000 | C1001: December | D1001: Q4 | E1001: 2025 | F1001: West | G1001: India | H1001: Maharashtra | I1001: Nagpur | J1001: Branch A | K1001: Finance | L1001: CC-1003 | M1001: P016 | N1001: Network Switch | O1001: Networking | P1001: Network Equipment | Q1001: 34733.42 | R1001: 30619.73 | S1001: 24454.69 | T1001: 3158 | U1001: 2450.36 | V1001: 3766.84 | W1001: 915.18 | X1001: 34745.07 | Y1001: 10278.73 | Z1001: -24466.34 | AA1001: -0.7292 | AB1001: 4113.7 | AC1001: 2778.67 | AD1001: 1597.74 | AE1001: 33552.49

Sheet Data Cleaning
A1: Transaction ID | B1: Date | C1: Month | D1: Quarter | E1: Year | F1: Region | G1: Country | H1: State | I1: City | J1: Branch | K1: Department | L1: Cost Center | M1: Product ID | N1: Product Name | O1: Category | P1: Sub Category | Q1: Revenue | R1: Budget Revenue | S1: COGS | T1: Operating Expense | U1: Marketing Expense | V1: Salary Expense | W1: Misc Expense | X1: Total Expense | Y1: Gross Profit | Z1: Net Profit | AA1: Profit Margin % | AB1: Budget Variance | AC1: Discount | AD1: Tax | AE1: Net Revenue | AF1: Clean City | AG1: Clean State | AH1: Clean Department | AI1: Clean Product Name | AJ1: Clean Cost Center | AL1: DATA QUALITY CHECKS
A2: TXN-00001 | B2: 45850 | C2: July | D2: ="Q"&INT(MOD(MONTH(B2)-4,12)/3)+1 -> Q2 | E2: ="FY"& (YEAR(B2)+(MONTH(B2)>=4)) -> FY2026 | F2: West | G2: India | H2: Goa | I2: Vasco da Gama | J2: Branch D | K2: Operations | L2: CC-1002 | M2: P019 | N2: Conference Camera | O2: Electronics | P2: Video Conferencing | Q2: 23278.76 | R2: 22815.81 | S2: 11971.99 | T2: 2376.09 | U2: 667.33 | V2: 2275.73 | W2: 997.48 | X2: 18288.61 | Y2: 11306.77 | Z2: =Q2-X2 -> 4990.15 | AA2: =Z2/Q2 -> 0.21436494 | AB2: 462.95 | AC2: 0 | AD2: 4190.18 | AE2: 27468.94 | AF2: =IF(tbl_FinancialData[[#This Row],[City]]="","Unknown",PROPER(TRIM(tbl_FinancialData[[#This Row],[City]]))) -> Vasco Da Gama | AG2: =_xlfn.LET(_xlpm.city,LOWER(TRIM(tbl_FinancialData[[#This Row],[City]])),_xlpm.st,PROPER(TRIM(tbl_FinancialData[[#This Row],[State]])),IF(_xlpm.city="pune","Maharashtra",IF(_xlpm.city="jamshedpur","Jharkhand",IF(_xlpm.city="bhilai","Chhattisgarh",IF(_xlpm.city="mumbai","Maharashtra",_xlpm.st))))) -> Goa | AH2: =_xlfn.LET(_xlpm.d,PROPER(TRIM(tbl_FinancialData[[#This Row],[Department]])),IF(_xlpm.d="It","IT",_xlpm.d)) -> Operations | AI2: =_xlfn.LET(_xlpm.pid,tbl_FinancialData[[#This Row],[Product ID]],_xlpm.n,PROPER(TRIM(tbl_FinancialData[[#This Row],[Product Name]])),IF(_xlpm.pid="P020","Document Scanner",IF(_xlpm.pid="P015","Network Router",SUBSTITUTE(SUBSTITUTE(_xlpm.n,"Crm","CRM"),"Ups","UPS")))) -> Conference Camera | AJ2: =UPPER(TRIM(tbl_FinancialData[[#This Row],[Cost Center]])) -> CC-1002
A3: TXN-00002 | B3: 45908 | C3: September | D3: ="Q"&INT(MOD(MONTH(B3)-4,12)/3)+1 -> Q2 | E3: ="FY"& (YEAR(B3)+(MONTH(B3)>=4)) -> FY2026 | F3: South | G3: India | H3: Tamil Nadu | I3: Chennai | J3: Branch D | K3: Sales | L3: CC-1003 | M3: P010 | N3: Mouse | O3: Accessories | P3: Computer Accessories | Q3: 2086.76 | R3: 1982.07 | S3: 1047.02 | T3: 207.57 | U3: 104.05 | V3: 247.61 | W3: 54.96 | X3: 1661.21 | Y3: 1039.74 | Z3: =Q3-X3 -> 425.55 | AA3: =Z3/Q3 -> 0.20392858 | AB3: 104.69 | AC3: 166.94 | AD3: 345.57 | AE3: 2265.39 | AF3: =IF(tbl_FinancialData[[#This Row],[City]]="","Unknown",PROPER(TRIM(tbl_FinancialData[[#This Row],[City]]))) -> Chennai | AG3: =_xlfn.LET(_xlpm.city,LOWER(TRIM(tbl_FinancialData[[#This Row],[City]])),_xlpm.st,PROPER(TRIM(tbl_FinancialData[[#This Row],[State]])),IF(_xlpm.city="pune","Maharashtra",IF(_xlpm.city="jamshedpur","Jharkhand",IF(_xlpm.city="bhilai","Chhattisgarh",IF(_xlpm.city="mumbai","Maharashtra",_xlpm.st))))) -> Tamil Nadu | AH3: =_xlfn.LET(_xlpm.d,PROPER(TRIM(tbl_FinancialData[[#This Row],[Department]])),IF(_xlpm.d="It","IT",_xlpm.d)) -> Sales | AI3: =_xlfn.LET(_xlpm.pid,tbl_FinancialData[[#This Row],[Product ID]],_xlpm.n,PROPER(TRIM(tbl_FinancialData[[#This Row],[Product Name]])),IF(_xlpm.pid="P020","Document Scanner",IF(_xlpm.pid="P015","Network Router",SUBSTITUTE(SUBSTITUTE(_xlpm.n,"Crm","CRM"),"Ups","UPS")))) -> Mouse | AJ3: =UPPER(TRIM(tbl_FinancialData[[#This Row],[Cost Center]])) -> CC-1003 | AL3: Check | AM3: Result | AN3: Status
A4: TXN-00003 | B4: 46076 | C4: February | D4: ="Q"&INT(MOD(MONTH(B4)-4,12)/3)+1 -> Q4 | E4: ="FY"& (YEAR(B4)+(MONTH(B4)>=4)) -> FY2026 | F4: North | G4: India | H4: Uttar Pradesh | I4: Lucknow | J4: Branch D | K4: Operations | L4: CC-1002 | M4: P009 | N4: Keyboard | O4: Accessories | P4: Computer Accessories | Q4: 1176.9 | R4: 1120.77 | S4: 757.9 | T4: 116.28 | U4: 93.16 | V4: 63.4 | W4: 27.88 | X4: 1058.62 | Y4: 419 | Z4: =Q4-X4 -> 118.28 | AA4: =Z4/Q4 -> 0.10050132 | AB4: 56.13 | AC4: 23.54 | AD4: 207.6 | AE4: 1360.97 | AF4: =IF(tbl_FinancialData[[#This Row],[City]]="","Unknown",PROPER(TRIM(tbl_FinancialData[[#This Row],[City]]))) -> Lucknow | AG4: =_xlfn.LET(_xlpm.city,LOWER(TRIM(tbl_FinancialData[[#This Row],[City]])),_xlpm.st,PROPER(TRIM(tbl_FinancialData[[#This Row],[State]])),IF(_xlpm.city="pune","Maharashtra",IF(_xlpm.city="jamshedpur","Jharkhand",IF(_xlpm.city="bhilai","Chhattisgarh",IF(_xlpm.city="mumbai","Maharashtra",_xlpm.st))))) -> Uttar Pradesh | AH4: =_xlfn.LET(_xlpm.d,PROPER(TRIM(tbl_FinancialData[[#This Row],[Department]])),IF(_xlpm.d="It","IT",_xlpm.d)) -> Operations | AI4: =_xlfn.LET(_xlpm.pid,tbl_FinancialData[[#This Row],[Product ID]],_xlpm.n,PROPER(TRIM(tbl_FinancialData[[#This Row],[Product Name]])),IF(_xlpm.pid="P020","Document Scanner",IF(_xlpm.pid="P015","Network Router",SUBSTITUTE(SUBSTITUTE(_xlpm.n,"Crm","CRM"),"Ups","UPS")))) -> Keyboard | AJ4: =UPPER(TRIM(tbl_FinancialData[[#This Row],[Cost Center]])) -> CC-1002 | AL4: Total Records | AM4: =ROWS(tbl_FinancialData[Transaction ID]) -> 1000 | AN4: =IF(AM4=1000,"PASS","CHECK") -> PASS
A5: TXN-00004 | B5: 45801 | C5: May | D5: ="Q"&INT(MOD(MONTH(B5)-4,12)/3)+1 -> Q1 | E5: ="FY"& (YEAR(B5)+(MONTH(B5)>=4)) -> FY2026 | F5: East | G5: India | H5: Odisha | I5: Bhubaneswar | J5: Branch C | K5: Marketing | L5: CC-1004 | M5: P002 | N5: Monitor | O5: Electronics | P5: Computing | Q5: 47762.94 | R5: 52452.38 | S5: 26669.38 | T5: 4567.83 | U5: 2811.05 | V5: 5583.19 | W5: 1889.44 | X5: 41520.9 | Y5: 21093.56 | Z5: =Q5-X5 -> 6242.04 | AA5: =Z5/Q5 -> 0.13068794 | AB5: -4689.44 | AC5: 2388.15 | AD5: 5444.98 | AE5: 50819.77 | AF5: =IF(tbl_FinancialData[[#This Row],[City]]="","Unknown",PROPER(TRIM(tbl_FinancialData[[#This Row],[City]]))) -> Bhubaneswar | AG5: =_xlfn.LET(_xlpm.city,LOWER(TRIM(tbl_FinancialData[[#This Row],[City]])),_xlpm.st,PROPER(TRIM(tbl_FinancialData[[#This Row],[State]])),IF(_xlpm.city="pune","Maharashtra",IF(_xlpm.city="jamshedpur","Jharkhand",IF(_xlpm.city="bhilai","Chhattisgarh",IF(_xlpm.city="mumbai","Maharashtra",_xlpm.st))))) -> Odisha | AH5: =_xlfn.LET(_xlpm.d,PROPER(TRIM(tbl_FinancialData[[#This Row],[Department]])),IF(_xlpm.d="It","IT",_xlpm.d)) -> Marketing | AI5: =_xlfn.LET(_xlpm.pid,tbl_FinancialData[[#This Row],[Product ID]],_xlpm.n,PROPER(TRIM(tbl_FinancialData[[#This Row],[Product Name]])),IF(_xlpm.pid="P020","Document Scanner",IF(_xlpm.pid="P015","Network Router",SUBSTITUTE(SUBSTITUTE(_xlpm.n,"Crm","CRM"),"Ups","UPS")))) -> Monitor | AJ5: =UPPER(TRIM(tbl_FinancialData[[#This Row],[Cost Center]])) -> CC-1004 | AL5: Duplicate Transaction IDs | AM5: =ROWS(tbl_FinancialData[Transaction ID])-ROWS(_xlfn.UNIQUE(tbl_FinancialData[Transaction ID])) -> 0 | AN5: =IF(AM5=0,"PASS","CHECK") -> PASS
A6: TXN-00005 | B6: 46027 | C6: January | D6: ="Q"&INT(MOD(MONTH(B6)-4,12)/3)+1 -> Q4 | E6: ="FY"& (YEAR(B6)+(MONTH(B6)>=4)) -> FY2026 | F6: South | G6: India | H6: Kerala | I6: Kochi | J6: Branch A | K6: Sales | L6: CC-1005 | M6: P001 | N6: Business Laptop | O6: Electronics | P6: Computing | Q6: 18810.62 | R6: 18781.73 | S6: 10354.06 | T6: 961.72 | U6: 713.39 | V6: 1822.89 | W6: 708.34 | X6: 14560.39 | Y6: 8456.55 | Z6: =Q6-X6 -> 4250.23 | AA6: =Z6/Q6 -> 0.22594843 | AB6: 28.88 | AC6: 940.53 | AD6: 3216.62 | AE6: 21086.7 | AF6: =IF(tbl_FinancialData[[#This Row],[City]]="","Unknown",PROPER(TRIM(tbl_FinancialData[[#This Row],[City]]))) -> Kochi | AG6: =_xlfn.LET(_xlpm.city,LOWER(TRIM(tbl_FinancialData[[#This Row],[City]])),_xlpm.st,PROPER(TRIM(tbl_FinancialData[[#This Row],[State]])),IF(_xlpm.city="pune","Maharashtra",IF(_xlpm.city="jamshedpur","Jharkhand",IF(_xlpm.city="bhilai","Chhattisgarh",IF(_xlpm.city="mumbai","Maharashtra",_xlpm.st))))) -> Kerala | AH6: =_xlfn.LET(_xlpm.d,PROPER(TRIM(tbl_FinancialData[[#This Row],[Department]])),IF(_xlpm.d="It","IT",_xlpm.d)) -> Sales | AI6: =_xlfn.LET(_xlpm.pid,tbl_FinancialData[[#This Row],[Product ID]],_xlpm.n,PROPER(TRIM(tbl_FinancialData[[#This Row],[Product Name]])),IF(_xlpm.pid="P020","Document Scanner",IF(_xlpm.pid="P015","Network Router",SUBSTITUTE(SUBSTITUTE(_xlpm.n,"Crm","CRM"),"Ups","UPS")))) -> Business Laptop | AJ6: =UPPER(TRIM(tbl_FinancialData[[#This Row],[Cost Center]])) -> CC-1005 | AL6: Blank Transaction IDs | AM6: =COUNTBLANK(tbl_FinancialData[Transaction ID]) -> 0 | AN6: =IF(AM6=0,"PASS","CHECK") -> PASS
A7: TXN-00006 | B7: 45788 | C7: May | D7: ="Q"&INT(MOD(MONTH(B7)-4,12)/3)+1 -> Q1 | E7: ="FY"& (YEAR(B7)+(MONTH(B7)>=4)) -> FY2026 | F7: Central | G7: India | H7: Madhya Pradesh | I7: Indore | J7: Branch A | K7: Sales | L7: CC-1005 | M7: P003 | N7: Printer | O7: Electronics | P7: Office Equipment | Q7: 41891.12 | R7: 43917.52 | S7: 23957.63 | T7: 5351.04 | U7: 3358.8 | V7: 4094.37 | W7: 764.91 | X7: 37526.76 | Y7: 17933.48 | Z7: =Q7-X7 -> 4364.36 | AA7: =Z7/Q7 -> 0.10418342 | AB7: -2026.4 | AC7: 837.82 | AD7: 2052.66 | AE7: 43105.96 | AF7: =IF(tbl_FinancialData[[#This Row],[City]]="","Unknown",PROPER(TRIM(tbl_FinancialData[[#This Row],[City]]))) -> Indore | AG7: =_xlfn.LET(_xlpm.city,LOWER(TRIM(tbl_FinancialData[[#This Row],[City]])),_xlpm.st,PROPER(TRIM(tbl_FinancialData[[#This Row],[State]])),IF(_xlpm.city="pune","Maharashtra",IF(_xlpm.city="jamshedpur","Jharkhand",IF(_xlpm.city="bhilai","Chhattisgarh",IF(_xlpm.city="mumbai","Maharashtra",_xlpm.st))))) -> Madhya Pradesh | AH7: =_xlfn.LET(_xlpm.d,PROPER(TRIM(tbl_FinancialData[[#This Row],[Department]])),IF(_xlpm.d="It","IT",_xlpm.d)) -> Sales | AI7: =_xlfn.LET(_xlpm.pid,tbl_FinancialData[[#This Row],[Product ID]],_xlpm.n,PROPER(TRIM(tbl_FinancialData[[#This Row],[Product Name]])),IF(_xlpm.pid="P020","Document Scanner",IF(_xlpm.pid="P015","Network Router",SUBSTITUTE(SUBSTITUTE(_xlpm.n,"Crm","CRM"),"Ups","UPS")))) -> Printer | AJ7: =UPPER(TRIM(tbl_FinancialData[[#This Row],[Cost Center]])) -> CC-1005 | AL7: Blank Dates | AM7: =COUNTBLANK(tbl_FinancialData[Date]) -> 0 | AN7: =IF(AM7=0,"PASS","CHECK") -> PASS
A8: TXN-00007 | B8: 45954 | C8: October | D8: ="Q"&INT(MOD(MONTH(B8)-4,12)/3)+1 -> Q3 | E8: ="FY"& (YEAR(B8)+(MONTH(B8)>=4)) -> FY2026 | F8: East | G8: India | H8: Odisha | I8: Bhubaneswar | J8: Branch C | K8: Sales | L8: CC-1001 | M8: P020 | N8: Document Scanner | O8: Electronics | P8: Office Equipment | Q8: 51914.87 | R8: 47855.1 | S8: 32449.92 | T8: 4837.81 | U8: 1983.1 | V8: 5992.44 | W8: 1607.3 | X8: 46870.57 | Y8: 19464.95 | Z8: =Q8-X8 -> 5044.3 | AA8: =Z8/Q8 -> 0.097164839 | AB8: 4059.77 | AC8: 2595.74 | AD8: 8877.44 | AE8: 58196.57 | AF8: =IF(tbl_FinancialData[[#This Row],[City]]="","Unknown",PROPER(TRIM(tbl_FinancialData[[#This Row],[City]]))) -> Bhubaneswar | AG8: =_xlfn.LET(_xlpm.city,LOWER(TRIM(tbl_FinancialData[[#This Row],[City]])),_xlpm.st,PROPER(TRIM(tbl_FinancialData[[#This Row],[State]])),IF(_xlpm.city="pune","Maharashtra",IF(_xlpm.city="jamshedpur","Jharkhand",IF(_xlpm.city="bhilai","Chhattisgarh",IF(_xlpm.city="mumbai","Maharashtra",_xlpm.st))))) -> Odisha | AH8: =_xlfn.LET(_xlpm.d,PROPER(TRIM(tbl_FinancialData[[#This Row],[Department]])),IF(_xlpm.d="It","IT",_xlpm.d)) -> Sales | AI8: =_xlfn.LET(_xlpm.pid,tbl_FinancialData[[#This Row],[Product ID]],_xlpm.n,PROPER(TRIM(tbl_FinancialData[[#This Row],[Product Name]])),IF(_xlpm.pid="P020","Document Scanner",IF(_xlpm.pid="P015","Network Router",SUBSTITUTE(SUBSTITUTE(_xlpm.n,"Crm","CRM"),"Ups","UPS")))) -> Document Scanner | AJ8: =UPPER(TRIM(tbl_FinancialData[[#This Row],[Cost Center]])) -> CC-1001 | AL8: Blank Revenue | AM8: =COUNTBLANK(tbl_FinancialData[Revenue]) -> 0 | AN8: =IF(AM8=0,"PASS","CHECK") -> PASS
A9: TXN-00008 | B9: 45917 | C9: September | D9: ="Q"&INT(MOD(MONTH(B9)-4,12)/3)+1 -> Q2 | E9: ="FY"& (YEAR(B9)+(MONTH(B9)>=4)) -> FY2026 | F9: West | G9: India | H9: Maharashtra | I9: Mumbai | J9: Branch B | K9: Finance | L9: CC-1004 | M9: P012 | N9: Accounting Software | O9: Software | P9: Business Software | Q9: 18661.59 | R9: 18238.04 | S9: 9504.37 | T9: 1465.01 | U9: 1566.53 | V9: 1152.74 | W9: 609.66 | X9: 14298.29 | Y9: 9157.22 | Z9: =Q9-X9 -> 4363.3 | AA9: =Z9/Q9 -> 0.2338118 | AB9: 423.55 | AC9: 0 | AD9: 2239.39 | AE9: 20900.98 | AF9: =IF(tbl_FinancialData[[#This Row],[City]]="","Unknown",PROPER(TRIM(tbl_FinancialData[[#This Row],[City]]))) -> Mumbai | AG9: =_xlfn.LET(_xlpm.city,LOWER(TRIM(tbl_FinancialData[[#This Row],[City]])),_xlpm.st,PROPER(TRIM(tbl_FinancialData[[#This Row],[State]])),IF(_xlpm.city="pune","Maharashtra",IF(_xlpm.city="jamshedpur","Jharkhand",IF(_xlpm.city="bhilai","Chhattisgarh",IF(_xlpm.city="mumbai","Maharashtra",_xlpm.st))))) -> Maharashtra | AH9: =_xlfn.LET(_xlpm.d,PROPER(TRIM(tbl_FinancialData[[#This Row],[Department]])),IF(_xlpm.d="It","IT",_xlpm.d)) -> Finance | AI9: =_xlfn.LET(_xlpm.pid,tbl_FinancialData[[#This Row],[Product ID]],_xlpm.n,PROPER(TRIM(tbl_FinancialData[[#This Row],[Product Name]])),IF(_xlpm.pid="P020","Document Scanner",IF(_xlpm.pid="P015","Network Router",SUBSTITUTE(SUBSTITUTE(_xlpm.n,"Crm","CRM"),"Ups","UPS")))) -> Accounting Software | AJ9: =UPPER(TRIM(tbl_FinancialData[[#This Row],[Cost Center]])) -> CC-1004 | AL9: Negative Revenue | AM9: =COUNTIF(tbl_FinancialData[Revenue],"<0") -> 0 | AN9: =IF(AM9=0,"PASS","CHECK") -> PASS
A10: TXN-00009 | B10: 46006 | C10: December | D10: ="Q"&INT(MOD(MONTH(B10)-4,12)/3)+1 -> Q3 | E10: ="FY"& (YEAR(B10)+(MONTH(B10)>=4)) -> FY2026 | F10: North | G10: India | H10: Uttar Pradesh | I10: Agra | J10: Branch A | K10: Finance | L10: CC-1001 | M10: P019 | N10: Conference Camera | O10: Electronics | P10: Video Conferencing | Q10: 27488.07 | R10: 25577.3 | S10: 14637.49 | T10: 2601.69 | U10: 1408.75 | V10: 1242.22 | W10: 519.17 | X10: 20409.32 | Y10: 12850.58 | Z10: =Q10-X10 -> 7078.75 | AA10: =Z10/Q10 -> 0.25752081 | AB10: 1910.77 | AC10: 549.76 | AD10: 4848.89 | AE10: 31787.2 | AF10: =IF(tbl_FinancialData[[#This Row],[City]]="","Unknown",PROPER(TRIM(tbl_FinancialData[[#This Row],[City]]))) -> Agra | AG10: =_xlfn.LET(_xlpm.city,LOWER(TRIM(tbl_FinancialData[[#This Row],[City]])),_xlpm.st,PROPER(TRIM(tbl_FinancialData[[#This Row],[State]])),IF(_xlpm.city="pune","Maharashtra",IF(_xlpm.city="jamshedpur","Jharkhand",IF(_xlpm.city="bhilai","Chhattisgarh",IF(_xlpm.city="mumbai","Maharashtra",_xlpm.st))))) -> Uttar Pradesh | AH10: =_xlfn.LET(_xlpm.d,PROPER(TRIM(tbl_FinancialData[[#This Row],[Department]])),IF(_xlpm.d="It","IT",_xlpm.d)) -> Finance | AI10: =_xlfn.LET(_xlpm.pid,tbl_FinancialData[[#This Row],[Product ID]],_xlpm.n,PROPER(TRIM(tbl_FinancialData[[#This Row],[Product Name]])),IF(_xlpm.pid="P020","Document Scanner",IF(_xlpm.pid="P015","Network Router",SUBSTITUTE(SUBSTITUTE(_xlpm.n,"Crm","CRM"),"Ups","UPS")))) -> Conference Camera | AJ10: =UPPER(TRIM(tbl_FinancialData[[#This Row],[Cost Center]])) -> CC-1001 | AL10: Negative Budget Revenue | AM10: =COUNTIF(tbl_FinancialData[Budget Revenue],"<0") -> 0 | AN10: =IF(AM10=0,"PASS","CHECK") -> PASS
A11: TXN-00010 | B11: 45860 | C11: July | D11: ="Q"&INT(MOD(MONTH(B11)-4,12)/3)+1 -> Q2 | E11: ="FY"& (YEAR(B11)+(MONTH(B11)>=4)) -> FY2026 | F11: North | G11: India | H11: Uttar Pradesh | I11: Lucknow | J11: Branch C | K11: Operations | L11: CC-1002 | M11: P005 | N11: Office Desk | O11: Furniture | P11: Office Furniture | Q11: 17627.99 | R11: 19112.48 | S11: 10707.67 | T11: 1512.88 | U11: 1074.22 | V11: 1540.96 | W11: 226.16 | X11: 15061.9 | Y11: 6920.32 | Z11: =Q11-X11 -> 2566.09 | AA11: =Z11/Q11 -> 0.14556906 | AB11: -1484.48 | AC11: 528.84 | AD11: 854.96 | AE11: 17954.11 | AF11: =IF(tbl_FinancialData[[#This Row],[City]]="","Unknown",PROPER(TRIM(tbl_FinancialData[[#This Row],[City]]))) -> Lucknow | AG11: =_xlfn.LET(_xlpm.city,LOWER(TRIM(tbl_FinancialData[[#This Row],[City]])),_xlpm.st,PROPER(TRIM(tbl_FinancialData[[#This Row],[State]])),IF(_xlpm.city="pune","Maharashtra",IF(_xlpm.city="jamshedpur","Jharkhand",IF(_xlpm.city="bhilai","Chhattisgarh",IF(_xlpm.city="mumbai","Maharashtra",_xlpm.st))))) -> Uttar Pradesh | AH11: =_xlfn.LET(_xlpm.d,PROPER(TRIM(tbl_FinancialData[[#This Row],[Department]])),IF(_xlpm.d="It","IT",_xlpm.d)) -> Operations | AI11: =_xlfn.LET(_xlpm.pid,tbl_FinancialData[[#This Row],[Product ID]],_xlpm.n,PROPER(TRIM(tbl_FinancialData[[#This Row],[Product Name]])),IF(_xlpm.pid="P020","Document Scanner",IF(_xlpm.pid="P015","Network Router",SUBSTITUTE(SUBSTITUTE(_xlpm.n,"Crm","CRM"),"Ups","UPS")))) -> Office Desk | AJ11: =UPPER(TRIM(tbl_FinancialData[[#This Row],[Cost Center]])) -> CC-1002
A12: TXN-00011 | B12: 46041 | C12: January | D12: ="Q"&INT(MOD(MONTH(B12)-4,12)/3)+1 -> Q4 | E12: ="FY"& (YEAR(B12)+(MONTH(B12)>=4)) -> FY2026 | F12: South | G12: India | H12: Kerala | I12: Thiruvananthapuram | J12: Branch B | K12: Finance | L12: CC-1001 | M12: P009 | N12: Keyboard | O12: Accessories | P12: Computer Accessories | Q12: 3190.87 | R12: 2847 | S12: 1984.13 | T12: 332.5 | U12: 83.21 | V12: 258.36 | W12: 57.2 | X12: 2715.4 | Y12: 1206.74 | Z12: =Q12-X12 -> 475.47 | AA12: =Z12/Q12 -> 0.14900952 | AB12: 343.87 | AC12: 159.54 | AD12: 151.57 | AE12: 3182.89 | AF12: =IF(tbl_FinancialData[[#This Row],[City]]="","Unknown",PROPER(TRIM(tbl_FinancialData[[#This Row],[City]]))) -> Thiruvananthapuram | AG12: =_xlfn.LET(_xlpm.city,LOWER(TRIM(tbl_FinancialData[[#This Row],[City]])),_xlpm.st,PROPER(TRIM(tbl_FinancialData[[#This Row],[State]])),IF(_xlpm.city="pune","Maharashtra",IF(_xlpm.city="jamshedpur","Jharkhand",IF(_xlpm.city="bhilai","Chhattisgarh",IF(_xlpm.city="mumbai","Maharashtra",_xlpm.st))))) -> Kerala | AH12: =_xlfn.LET(_xlpm.d,PROPER(TRIM(tbl_FinancialData[[#This Row],[Department]])),IF(_xlpm.d="It","IT",_xlpm.d)) -> Finance | AI12: =_xlfn.LET(_xlpm.pid,tbl_FinancialData[[#This Row],[Product ID]],_xlpm.n,PROPER(TRIM(tbl_FinancialData[[#This Row],[Product Name]])),IF(_xlpm.pid="P020","Document Scanner",IF(_xlpm.pid="P015","Network Router",SUBSTITUTE(SUBSTITUTE(_xlpm.n,"Crm","CRM"),"Ups","UPS")))) -> Keyboard | AJ12: =UPPER(TRIM(tbl_FinancialData[[#This Row],[Cost Center]])) -> CC-1001 | AL12: FINANCIAL VALIDATION
A13: TXN-00012 | B13: 45875 | C13: August | D13: ="Q"&INT(MOD(MONTH(B13)-4,12)/3)+1 -> Q2 | E13: ="FY"& (YEAR(B13)+(MONTH(B13)>=4)) -> FY2026 | F13: East | G13: India | H13: Jharkhand | I13: Ranchi | J13: Branch C | K13: Sales | L13: CC-1001 | M13: P018 | N13: Projector | O13: Electronics | P13: Presentation | Q13: 78448.53 | R13: 75105.25 | S13: 50081.24 | T13: 9051.22 | U13: 4792.27 | V13: 6461.97 | W13: 1448.54 | X13: 71835.23 | Y13: 28367.29 | Z13: =Q13-X13 -> 6613.3 | AA13: =Z13/Q13 -> 0.084301133 | AB13: 3343.28 | AC13: 0 | AD13: 14120.74 | AE13: 92569.27 | AF13: =IF(tbl_FinancialData[[#This Row],[City]]="","Unknown",PROPER(TRIM(tbl_FinancialData[[#This Row],[City]]))) -> Ranchi | AG13: =_xlfn.LET(_xlpm.city,LOWER(TRIM(tbl_FinancialData[[#This Row],[City]])),_xlpm.st,PROPER(TRIM(tbl_FinancialData[[#This Row],[State]])),IF(_xlpm.city="pune","Maharashtra",IF(_xlpm.city="jamshedpur","Jharkhand",IF(_xlpm.city="bhilai","Chhattisgarh",IF(_xlpm.city="mumbai","Maharashtra",_xlpm.st))))) -> Jharkhand | AH13: =_xlfn.LET(_xlpm.d,PROPER(TRIM(tbl_FinancialData[[#This Row],[Department]])),IF(_xlpm.d="It","IT",_xlpm.d)) -> Sales | AI13: =_xlfn.LET(_xlpm.pid,tbl_FinancialData[[#This Row],[Product ID]],_xlpm.n,PROPER(TRIM(tbl_FinancialData[[#This Row],[Product Name]])),IF(_xlpm.pid="P020","Document Scanner",IF(_xlpm.pid="P015","Network Router",SUBSTITUTE(SUBSTITUTE(_xlpm.n,"Crm","CRM"),"Ups","UPS")))) -> Projector | AJ13: =UPPER(TRIM(tbl_FinancialData[[#This Row],[Cost Center]])) -> CC-1001
A14: TXN-00013 | B14: 45784 | C14: May | D14: ="Q"&INT(MOD(MONTH(B14)-4,12)/3)+1 -> Q1 | E14: ="FY"& (YEAR(B14)+(MONTH(B14)>=4)) -> FY2026 | F14: Central | G14: India | H14: Uttar Pradesh | I14: Lucknow | J14: Branch A | K14: Sales | L14: CC-1003 | M14: P020 | N14: Document Scanner | O14: Electronics | P14: Office Equipment | Q14: 72701.69 | R14: 77980.53 | S14: 36364.92 | T14: 4575.14 | U14: 6063.76 | V14: 6435.14 | W14: 750.42 | X14: 54189.38 | Y14: 36336.77 | Z14: =Q14-X14 -> 18512.31 | AA14: =Z14/Q14 -> 0.25463383 | AB14: -5278.83 | AC14: 0 | AD14: 13086.3 | AE14: 85788 | AF14: =IF(tbl_FinancialData[[#This Row],[City]]="","Unknown",PROPER(TRIM(tbl_FinancialData[[#This Row],[City]]))) -> Lucknow | AG14: =_xlfn.LET(_xlpm.city,LOWER(TRIM(tbl_FinancialData[[#This Row],[City]])),_xlpm.st,PROPER(TRIM(tbl_FinancialData[[#This Row],[State]])),IF(_xlpm.city="pune","Maharashtra",IF(_xlpm.city="jamshedpur","Jharkhand",IF(_xlpm.city="bhilai","Chhattisgarh",IF(_xlpm.city="mumbai","Maharashtra",_xlpm.st))))) -> Uttar Pradesh | AH14: =_xlfn.LET(_xlpm.d,PROPER(TRIM(tbl_FinancialData[[#This Row],[Department]])),IF(_xlpm.d="It","IT",_xlpm.d)) -> Sales | AI14: =_xlfn.LET(_xlpm.pid,tbl_FinancialData[[#This Row],[Product ID]],_xlpm.n,PROPER(TRIM(tbl_FinancialData[[#This Row],[Product Name]])),IF(_xlpm.pid="P020","Document Scanner",IF(_xlpm.pid="P015","Network Router",SUBSTITUTE(SUBSTITUTE(_xlpm.n,"Crm","CRM"),"Ups","UPS")))) -> Document Scanner | AJ14: =UPPER(TRIM(tbl_FinancialData[[#This Row],[Cost Center]])) -> CC-1003 | AL14: Validation Check | AM14: Invalid Rows | AN14: Status
A15: TXN-00014 | B15: 46096 | C15: March | D15: ="Q"&INT(MOD(MONTH(B15)-4,12)/3)+1 -> Q4 | E15: ="FY"& (YEAR(B15)+(MONTH(B15)>=4)) -> FY2026 | F15: South | G15: India | H15: Tamil Nadu | I15: Coimbatore | J15: Branch B | K15: Operations | L15: CC-1005 | M15: P009 | N15: Keyboard | O15: Accessories | P15: Computer Accessories | Q15: 1957.06 | R15: 2012.19 | S15: 1023.38 | T15: 155.23 | U15: 143.59 | V15: 191.16 | W15: 40.67 | X15: 1554.03 | Y15: 933.68 | Z15: =Q15-X15 -> 403.03 | AA15: =Z15/Q15 -> 0.20593646 | AB15: -55.13 | AC15: 97.85 | AD15: 223.1 | AE15: 2082.31 | AF15: =IF(tbl_FinancialData[[#This Row],[City]]="","Unknown",PROPER(TRIM(tbl_FinancialData[[#This Row],[City]]))) -> Coimbatore | AG15: =_xlfn.LET(_xlpm.city,LOWER(TRIM(tbl_FinancialData[[#This Row],[City]])),_xlpm.st,PROPER(TRIM(tbl_FinancialData[[#This Row],[State]])),IF(_xlpm.city="pune","Maharashtra",IF(_xlpm.city="jamshedpur","Jharkhand",IF(_xlpm.city="bhilai","Chhattisgarh",IF(_xlpm.city="mumbai","Maharashtra",_xlpm.st))))) -> Tamil Nadu | AH15: =_xlfn.LET(_xlpm.d,PROPER(TRIM(tbl_FinancialData[[#This Row],[Department]])),IF(_xlpm.d="It","IT",_xlpm.d)) -> Operations | AI15: =_xlfn.LET(_xlpm.pid,tbl_FinancialData[[#This Row],[Product ID]],_xlpm.n,PROPER(TRIM(tbl_FinancialData[[#This Row],[Product Name]])),IF(_xlpm.pid="P020","Document Scanner",IF(_xlpm.pid="P015","Network Router",SUBSTITUTE(SUBSTITUTE(_xlpm.n,"Crm","CRM"),"Ups","UPS")))) -> Keyboard | AJ15: =UPPER(TRIM(tbl_FinancialData[[#This Row],[Cost Center]])) -> CC-1005 | AL15: Total Expense Calculation | AM15: {=SUMPRODUCT(--(ABS((tbl_FinancialData[COGS]+tbl_FinancialData[Operating Expense]+tbl_FinancialData[Marketing Expense]+tbl_FinancialData[Salary Expense]+tbl_FinancialData[Misc Expense])-tbl_FinancialData[Total Expense])>0.05))} -> 0 | AN15: =IF(AM15=0,"PASS","CHECK") -> PASS
A16: TXN-00015 | B16: 45769 | C16: April | D16: ="Q"&INT(MOD(MONTH(B16)-4,12)/3)+1 -> Q1 | E16: ="FY"& (YEAR(B16)+(MONTH(B16)>=4)) -> FY2026 | F16: South | G16: India | H16: Tamil Nadu | I16: Coimbatore | J16: Branch A | K16: Finance | L16: CC-1003 | M16: P002 | N16: Monitor | O16: Electronics | P16: Computing | Q16: 39175.98 | R16: 42336.59 | S16: 26929.57 | T16: 2680.22 | U16: 2250.56 | V16: 3359.74 | W16: 1445.57 | X16: 36665.67 | Y16: 12246.4 | Z16: =Q16-X16 -> 2510.31 | AA16: =Z16/Q16 -> 0.064077784 | AB16: -3160.61 | AC16: 0 | AD16: 7051.68 | AE16: 46227.65 | AF16: =IF(tbl_FinancialData[[#This Row],[City]]="","Unknown",PROPER(TRIM(tbl_FinancialData[[#This Row],[City]]))) -> Coimbatore | AG16: =_xlfn.LET(_xlpm.city,LOWER(TRIM(tbl_FinancialData[[#This Row],[City]])),_xlpm.st,PROPER(TRIM(tbl_FinancialData[[#This Row],[State]])),IF(_xlpm.city="pune","Maharashtra",IF(_xlpm.city="jamshedpur","Jharkhand",IF(_xlpm.city="bhilai","Chhattisgarh",IF(_xlpm.city="mumbai","Maharashtra",_xlpm.st))))) -> Tamil Nadu | AH16: =_xlfn.LET(_xlpm.d,PROPER(TRIM(tbl_FinancialData[[#This Row],[Department]])),IF(_xlpm.d="It","IT",_xlpm.d)) -> Finance | AI16: =_xlfn.LET(_xlpm.pid,tbl_FinancialData[[#This Row],[Product ID]],_xlpm.n,PROPER(TRIM(tbl_FinancialData[[#This Row],[Product Name]])),IF(_xlpm.pid="P020","Document Scanner",IF(_xlpm.pid="P015","Network Router",SUBSTITUTE(SUBSTITUTE(_xlpm.n,"Crm","CRM"),"Ups","UPS")))) -> Monitor | AJ16: =UPPER(TRIM(tbl_FinancialData[[#This Row],[Cost Center]])) -> CC-1003 | AL16: Gross Profit Calculation | AM16: {=SUMPRODUCT(--(ABS((tbl_FinancialData[Revenue]-tbl_FinancialData[COGS])-tbl_FinancialData[Gross Profit])>0.05))} -> 0 | AN16: =IF(AM16=0,"PASS","CHECK") -> PASS
A17: TXN-00016 | B17: 45905 | C17: September | D17: ="Q"&INT(MOD(MONTH(B17)-4,12)/3)+1 -> Q2 | E17: ="FY"& (YEAR(B17)+(MONTH(B17)>=4)) -> FY2026 | F17: Central | G17: India | H17: Madhya Pradesh | I17: Indore | J17: Branch C | K17: Marketing | L17: CC-1005 | M17: P017 | N17: UPS System | O17: Electronics | P17: Power Equipment | Q17: 48086.6 | R17: 56458.46 | S17: 23951.12 | T17: 3580.32 | U17: 1798.88 | V17: 2956.27 | W17: 1297.61 | X17: 33584.21 | Y17: 24135.48 | Z17: =Q17-X17 -> 14502.39 | AA17: =Z17/Q17 -> 0.30158901 | AB17: -8371.85 | AC17: 1442.6 | AD17: 5597.28 | AE17: 52241.29 | AF17: =IF(tbl_FinancialData[[#This Row],[City]]="","Unknown",PROPER(TRIM(tbl_FinancialData[[#This Row],[City]]))) -> Indore | AG17: =_xlfn.LET(_xlpm.city,LOWER(TRIM(tbl_FinancialData[[#This Row],[City]])),_xlpm.st,PROPER(TRIM(tbl_FinancialData[[#This Row],[State]])),IF(_xlpm.city="pune","Maharashtra",IF(_xlpm.city="jamshedpur","Jharkhand",IF(_xlpm.city="bhilai","Chhattisgarh",IF(_xlpm.city="mumbai","Maharashtra",_xlpm.st))))) -> Madhya Pradesh | AH17: =_xlfn.LET(_xlpm.d,PROPER(TRIM(tbl_FinancialData[[#This Row],[Department]])),IF(_xlpm.d="It","IT",_xlpm.d)) -> Marketing | AI17: =_xlfn.LET(_xlpm.pid,tbl_FinancialData[[#This Row],[Product ID]],_xlpm.n,PROPER(TRIM(tbl_FinancialData[[#This Row],[Product Name]])),IF(_xlpm.pid="P020","Document Scanner",IF(_xlpm.pid="P015","Network Router",SUBSTITUTE(SUBSTITUTE(_xlpm.n,"Crm","CRM"),"Ups","UPS")))) -> UPS System | AJ17: =UPPER(TRIM(tbl_FinancialData[[#This Row],[Cost Center]])) -> CC-1005 | AL17: Net Profit Calculation | AM17: {=SUMPRODUCT(--(ABS((tbl_FinancialData[Revenue]-tbl_FinancialData[Total Expense])-tbl_FinancialData[Net Profit])>0.05))} -> 0 | AN17: =IF(AM17=0,"PASS","CHECK") -> PASS
A18: TXN-00017 | B18: 45801 | C18: May | D18: ="Q"&INT(MOD(MONTH(B18)-4,12)/3)+1 -> Q1 | E18: ="FY"& (YEAR(B18)+(MONTH(B18)>=4)) -> FY2026 | F18: West | G18: India | H18: Rajasthan | I18: Jodhpur | J18: Branch D | K18: Sales | L18: CC-1002 | M18: P010 | N18: Mouse | O18: Accessories | P18: Computer Accessories | Q18: 9607.66 | R18: 10463.75 | S18: 6231.49 | T18: 756.69 | U18: 423.54 | V18: 1006.39 | W18: 368.49 | X18: 8786.61 | Y18: 3376.17 | Z18: =Q18-X18 -> 821.05 | AA18: =Z18/Q18 -> 0.085457853 | AB18: -856.09 | AC18: 768.61 | AD18: 1591.03 | AE18: 10430.08 | AF18: =IF(tbl_FinancialData[[#This Row],[City]]="","Unknown",PROPER(TRIM(tbl_FinancialData[[#This Row],[City]]))) -> Jodhpur | AG18: =_xlfn.LET(_xlpm.city,LOWER(TRIM(tbl_FinancialData[[#This Row],[City]])),_xlpm.st,PROPER(TRIM(tbl_FinancialData[[#This Row],[State]])),IF(_xlpm.city="pune","Maharashtra",IF(_xlpm.city="jamshedpur","Jharkhand",IF(_xlpm.city="bhilai","Chhattisgarh",IF(_xlpm.city="mumbai","Maharashtra",_xlpm.st))))) -> Rajasthan | AH18: =_xlfn.LET(_xlpm.d,PROPER(TRIM(tbl_FinancialData[[#This Row],[Department]])),IF(_xlpm.d="It","IT",_xlpm.d)) -> Sales | AI18: =_xlfn.LET(_xlpm.pid,tbl_FinancialData[[#This Row],[Product ID]],_xlpm.n,PROPER(TRIM(tbl_FinancialData[[#This Row],[Product Name]])),IF(_xlpm.pid="P020","Document Scanner",IF(_xlpm.pid="P015","Network Router",SUBSTITUTE(SUBSTITUTE(_xlpm.n,"Crm","CRM"),"Ups","UPS")))) -> Mouse | AJ18: =UPPER(TRIM(tbl_FinancialData[[#This Row],[Cost Center]])) -> CC-1002 | AL18: Budget Variance Calculation | AM18: {=SUMPRODUCT(--(ABS((tbl_FinancialData[Revenue]-tbl_FinancialData[Budget Revenue])-tbl_FinancialData[Budget Variance])>0.05))} -> 0 | AN18: =IF(AM18=0,"PASS","CHECK") -> PASS
A19: TXN-00018 | B19: 46060 | C19: February | D19: ="Q"&INT(MOD(MONTH(B19)-4,12)/3)+1 -> Q4 | E19: ="FY"& (YEAR(B19)+(MONTH(B19)>=4)) -> FY2026 | F19: West | G19: India | H19: Rajasthan | I19: pune | J19: Branch D | K19: Marketing | L19: CC-1004 | M19: P019 | N19: Conference Camera | O19: Electronics | P19: Video Conferencing | Q19: 33050.48 | R19: 30016.27 | S19: 20451.22 | T19: 1747.56 | U19: 1826.5 | V19: 2756.79 | W19: 661.97 | X19: 27444.03 | Y19: 12599.27 | Z19: =Q19-X19 -> 5606.45 | AA19: =Z19/Q19 -> 0.16963294 | AB19: 3034.21 | AC19: 1652.52 | AD19: 1569.9 | AE19: 32967.85 | AF19: =IF(tbl_FinancialData[[#This Row],[City]]="","Unknown",PROPER(TRIM(tbl_FinancialData[[#This Row],[City]]))) -> Pune | AG19: =_xlfn.LET(_xlpm.city,LOWER(TRIM(tbl_FinancialData[[#This Row],[City]])),_xlpm.st,PROPER(TRIM(tbl_FinancialData[[#This Row],[State]])),IF(_xlpm.city="pune","Maharashtra",IF(_xlpm.city="jamshedpur","Jharkhand",IF(_xlpm.city="bhilai","Chhattisgarh",IF(_xlpm.city="mumbai","Maharashtra",_xlpm.st))))) -> Maharashtra | AH19: =_xlfn.LET(_xlpm.d,PROPER(TRIM(tbl_FinancialData[[#This Row],[Department]])),IF(_xlpm.d="It","IT",_xlpm.d)) -> Marketing | AI19: =_xlfn.LET(_xlpm.pid,tbl_FinancialData[[#This Row],[Product ID]],_xlpm.n,PROPER(TRIM(tbl_FinancialData[[#This Row],[Product Name]])),IF(_xlpm.pid="P020","Document Scanner",IF(_xlpm.pid="P015","Network Router",SUBSTITUTE(SUBSTITUTE(_xlpm.n,"Crm","CRM"),"Ups","UPS")))) -> Conference Camera | AJ19: =UPPER(TRIM(tbl_FinancialData[[#This Row],[Cost Center]])) -> CC-1004 | AL19: Net Revenue Calculation | AM19: {=SUMPRODUCT(--(ABS((tbl_FinancialData[Revenue]-tbl_FinancialData[Discount]+tbl_FinancialData[Tax])-tbl_FinancialData[Net Revenue])>0.05))} -> 0 | AN19: =IF(AM19=0,"PASS","CHECK") -> PASS
A20: TXN-00019 | B20: 45927 | C20: September | D20: ="Q"&INT(MOD(MONTH(B20)-4,12)/3)+1 -> Q2 | E20: ="FY"& (YEAR(B20)+(MONTH(B20)>=4)) -> FY2026 | F20: North | G20: India | H20: Haryana | I20: Faridabad | J20: Branch C | K20: Sales | L20: CC-1001 | M20: P008 | N20: Headset | O20: Accessories | P20: Audio | Q20: 6337.58 | R20: 6761.36 | S20: 3171.85 | T20: 343.08 | U20: 377.33 | V20: 527.61 | W20: 204.77 | X20: 4624.64 | Y20: 3165.73 | Z20: =Q20-X20 -> 1712.94 | AA20: =Z20/Q20 -> 0.27028298 | AB20: -423.78 | AC20: 316.88 | AD20: 1083.73 | AE20: 7104.43 | AF20: =IF(tbl_FinancialData[[#This Row],[City]]="","Unknown",PROPER(TRIM(tbl_FinancialData[[#This Row],[City]]))) -> Faridabad | AG20: =_xlfn.LET(_xlpm.city,LOWER(TRIM(tbl_FinancialData[[#This Row],[City]])),_xlpm.st,PROPER(TRIM(tbl_FinancialData[[#This Row],[State]])),IF(_xlpm.city="pune","Maharashtra",IF(_xlpm.city="jamshedpur","Jharkhand",IF(_xlpm.city="bhilai","Chhattisgarh",IF(_xlpm.city="mumbai","Maharashtra",_xlpm.st))))) -> Haryana | AH20: =_xlfn.LET(_xlpm.d,PROPER(TRIM(tbl_FinancialData[[#This Row],[Department]])),IF(_xlpm.d="It","IT",_xlpm.d)) -> Sales | AI20: =_xlfn.LET(_xlpm.pid,tbl_FinancialData[[#This Row],[Product ID]],_xlpm.n,PROPER(TRIM(tbl_FinancialData[[#This Row],[Product Name]])),IF(_xlpm.pid="P020","Document Scanner",IF(_xlpm.pid="P015","Network Router",SUBSTITUTE(SUBSTITUTE(_xlpm.n,"Crm","CRM"),"Ups","UPS")))) -> Headset | AJ20: =UPPER(TRIM(tbl_FinancialData[[#This Row],[Cost Center]])) -> CC-1001 | AL20: Profit Margin Calculation | AM20: {=SUMPRODUCT(--(ABS((tbl_FinancialData[Net Profit]/IF(tbl_FinancialData[Revenue]=0,1,tbl_FinancialData[Revenue]))-tbl_FinancialData[Profit Margin %])>0.0001))} -> 0 | AN20: =IF(AM20=0,"PASS","CHECK") -> PASS
A21: TXN-00020 | B21: 45871 | C21: August | D21: ="Q"&INT(MOD(MONTH(B21)-4,12)/3)+1 -> Q2 | E21: ="FY"& (YEAR(B21)+(MONTH(B21)>=4)) -> FY2026 | F21: West | G21: India | H21: Goa | I21: Panaji | J21: Branch D | K21: Sales | L21: CC-1004 | M21: P005 | N21: Office Desk | O21: Furniture | P21: Office Furniture | Q21: 9626.48 | R21: 9708.25 | S21: 6211.39 | T21: 526.14 | U21: 813.33 | V21: 725.72 | W21: 177.06 | X21: 8453.64 | Y21: 3415.09 | Z21: =Q21-X21 -> 1172.84 | AA21: =Z21/Q21 -> 0.12183477 | AB21: -81.77 | AC21: 0 | AD21: 481.32 | AE21: 10107.8 | AF21: =IF(tbl_FinancialData[[#This Row],[City]]="","Unknown",PROPER(TRIM(tbl_FinancialData[[#This Row],[City]]))) -> Panaji | AG21: =_xlfn.LET(_xlpm.city,LOWER(TRIM(tbl_FinancialData[[#This Row],[City]])),_xlpm.st,PROPER(TRIM(tbl_FinancialData[[#This Row],[State]])),IF(_xlpm.city="pune","Maharashtra",IF(_xlpm.city="jamshedpur","Jharkhand",IF(_xlpm.city="bhilai","Chhattisgarh",IF(_xlpm.city="mumbai","Maharashtra",_xlpm.st))))) -> Goa | AH21: =_xlfn.LET(_xlpm.d,PROPER(TRIM(tbl_FinancialData[[#This Row],[Department]])),IF(_xlpm.d="It","IT",_xlpm.d)) -> Sales | AI21: =_xlfn.LET(_xlpm.pid,tbl_FinancialData[[#This Row],[Product ID]],_xlpm.n,PROPER(TRIM(tbl_FinancialData[[#This Row],[Product Name]])),IF(_xlpm.pid="P020","Document Scanner",IF(_xlpm.pid="P015","Network Router",SUBSTITUTE(SUBSTITUTE(_xlpm.n,"Crm","CRM"),"Ups","UPS")))) -> Office Desk | AJ21: =UPPER(TRIM(tbl_FinancialData[[#This Row],[Cost Center]])) -> CC-1004
A22: TXN-00021 | B22: 45984 | C22: November | D22: ="Q"&INT(MOD(MONTH(B22)-4,12)/3)+1 -> Q3 | E22: ="FY"& (YEAR(B22)+(MONTH(B22)>=4)) -> FY2026 | F22: South | G22: India | H22: Kerala | I22: Kochi | J22: Branch C | K22: Operations | L22: CC-1005 | M22: P003 | N22: Printer | O22: Electronics | P22: Office Equipment | Q22: 28563.85 | R22: 31630.29 | S22: 13809.32 | T22: 1693.43 | U22: 799.51 | V22: 1235.62 | W22: 1140.87 | X22: 18678.76 | Y22: 14754.53 | Z22: =Q22-X22 -> 9885.09 | AA22: =Z22/Q22 -> 0.34606995 | AB22: -3066.44 | AC22: 1428.19 | AD22: 3256.28 | AE22: 30391.94 | AF22: =IF(tbl_FinancialData[[#This Row],[City]]="","Unknown",PROPER(TRIM(tbl_FinancialData[[#This Row],[City]]))) -> Kochi | AG22: =_xlfn.LET(_xlpm.city,LOWER(TRIM(tbl_FinancialData[[#This Row],[City]])),_xlpm.st,PROPER(TRIM(tbl_FinancialData[[#This Row],[State]])),IF(_xlpm.city="pune","Maharashtra",IF(_xlpm.city="jamshedpur","Jharkhand",IF(_xlpm.city="bhilai","Chhattisgarh",IF(_xlpm.city="mumbai","Maharashtra",_xlpm.st))))) -> Kerala | AH22: =_xlfn.LET(_xlpm.d,PROPER(TRIM(tbl_FinancialData[[#This Row],[Department]])),IF(_xlpm.d="It","IT",_xlpm.d)) -> Operations | AI22: =_xlfn.LET(_xlpm.pid,tbl_FinancialData[[#This Row],[Product ID]],_xlpm.n,PROPER(TRIM(tbl_FinancialData[[#This Row],[Product Name]])),IF(_xlpm.pid="P020","Document Scanner",IF(_xlpm.pid="P015","Network Router",SUBSTITUTE(SUBSTITUTE(_xlpm.n,"Crm","CRM"),"Ups","UPS")))) -> Printer | AJ22: =UPPER(TRIM(tbl_FinancialData[[#This Row],[Cost Center]])) -> CC-1005 | AL22: FINAL CLEANING VALIDATION
A23: TXN-00022 | B23: 45965 | C23: November | D23: ="Q"&INT(MOD(MONTH(B23)-4,12)/3)+1 -> Q3 | E23: ="FY"& (YEAR(B23)+(MONTH(B23)>=4)) -> FY2026 | F23: West | G23: India | H23: Maharashtra | I23: Nagpur | J23: Branch D | K23: Sales | L23: CC-1005 | M23: P010 | N23: Mouse | O23: Accessories | P23: Computer Accessories | Q23: 11029.55 | R23: 10569.26 | S23: 5334.7 | T23: 1375.11 | U23: 634.94 | V23: 917.11 | W23: 374.33 | X23: 8636.19 | Y23: 5694.85 | Z23: =Q23-X23 -> 2393.36 | AA23: =Z23/Q23 -> 0.21699525 | AB23: 460.28 | AC23: 551.48 | AD23: 1886.05 | AE23: 12364.12 | AF23: =IF(tbl_FinancialData[[#This Row],[City]]="","Unknown",PROPER(TRIM(tbl_FinancialData[[#This Row],[City]]))) -> Nagpur | AG23: =_xlfn.LET(_xlpm.city,LOWER(TRIM(tbl_FinancialData[[#This Row],[City]])),_xlpm.st,PROPER(TRIM(tbl_FinancialData[[#This Row],[State]])),IF(_xlpm.city="pune","Maharashtra",IF(_xlpm.city="jamshedpur","Jharkhand",IF(_xlpm.city="bhilai","Chhattisgarh",IF(_xlpm.city="mumbai","Maharashtra",_xlpm.st))))) -> Maharashtra | AH23: =_xlfn.LET(_xlpm.d,PROPER(TRIM(tbl_FinancialData[[#This Row],[Department]])),IF(_xlpm.d="It","IT",_xlpm.d)) -> Sales | AI23: =_xlfn.LET(_xlpm.pid,tbl_FinancialData[[#This Row],[Product ID]],_xlpm.n,PROPER(TRIM(tbl_FinancialData[[#This Row],[Product Name]])),IF(_xlpm.pid="P020","Document Scanner",IF(_xlpm.pid="P015","Network Router",SUBSTITUTE(SUBSTITUTE(_xlpm.n,"Crm","CRM"),"Ups","UPS")))) -> Mouse | AJ23: =UPPER(TRIM(tbl_FinancialData[[#This Row],[Cost Center]])) -> CC-1005
A24: TXN-00023 | B24: 46005 | C24: December | D24: ="Q"&INT(MOD(MONTH(B24)-4,12)/3)+1 -> Q3 | E24: ="FY"& (YEAR(B24)+(MONTH(B24)>=4)) -> FY2026 | F24: North | G24: India | H24: Uttar Pradesh | I24: Agra | J24: Branch D | K24: Operations | L24: CC-1002 | M24: P003 | N24: Printer | O24: Electronics | P24: Office Equipment | Q24: 49438.08 | R24: 51597.79 | S24: 34900.89 | T24: 3998.96 | U24: 4324.71 | V24: 5558.23 | W24: 833.16 | X24: 49615.95 | Y24: 14537.19 | Z24: =Q24-X24 -> -177.87 | AA24: =Z24/Q24 -> -0.0035978339 | AB24: -2159.7 | AC24: 0 | AD24: 2471.9 | AE24: 51909.99 | AF24: =IF(tbl_FinancialData[[#This Row],[City]]="","Unknown",PROPER(TRIM(tbl_FinancialData[[#This Row],[City]]))) -> Agra | AG24: =_xlfn.LET(_xlpm.city,LOWER(TRIM(tbl_FinancialData[[#This Row],[City]])),_xlpm.st,PROPER(TRIM(tbl_FinancialData[[#This Row],[State]])),IF(_xlpm.city="pune","Maharashtra",IF(_xlpm.city="jamshedpur","Jharkhand",IF(_xlpm.city="bhilai","Chhattisgarh",IF(_xlpm.city="mumbai","Maharashtra",_xlpm.st))))) -> Uttar Pradesh | AH24: =_xlfn.LET(_xlpm.d,PROPER(TRIM(tbl_FinancialData[[#This Row],[Department]])),IF(_xlpm.d="It","IT",_xlpm.d)) -> Operations | AI24: =_xlfn.LET(_xlpm.pid,tbl_FinancialData[[#This Row],[Product ID]],_xlpm.n,PROPER(TRIM(tbl_FinancialData[[#This Row],[Product Name]])),IF(_xlpm.pid="P020","Document Scanner",IF(_xlpm.pid="P015","Network Router",SUBSTITUTE(SUBSTITUTE(_xlpm.n,"Crm","CRM"),"Ups","UPS")))) -> Printer | AJ24: =UPPER(TRIM(tbl_FinancialData[[#This Row],[Cost Center]])) -> CC-1002 | AL24: Validation Check | AM24: Result | AN24: Status
A25: TXN-00024 | B25: 46000 | C25: December | D25: ="Q"&INT(MOD(MONTH(B25)-4,12)/3)+1 -> Q3 | E25: ="FY"& (YEAR(B25)+(MONTH(B25)>=4)) -> FY2026 | F25: North | G25: India | H25: Haryana | I25: Panipat | J25: Branch A | K25: Operations | L25: CC-1005 | M25: P010 | N25: Mouse | O25: Accessories | P25: Computer Accessories | Q25: 1711.26 | R25: 1650.61 | S25: 869.94 | T25: 180.95 | U25: 112.74 | V25: 188.58 | W25: 61.14 | X25: 1413.34 | Y25: 841.33 | Z25: =Q25-X25 -> 297.92 | AA25: =Z25/Q25 -> 0.17409394 | AB25: 60.65 | AC25: 136.9 | AD25: 188.92 | AE25: 1763.29 | AF25: =IF(tbl_FinancialData[[#This Row],[City]]="","Unknown",PROPER(TRIM(tbl_FinancialData[[#This Row],[City]]))) -> Panipat | AG25: =_xlfn.LET(_xlpm.city,LOWER(TRIM(tbl_FinancialData[[#This Row],[City]])),_xlpm.st,PROPER(TRIM(tbl_FinancialData[[#This Row],[State]])),IF(_xlpm.city="pune","Maharashtra",IF(_xlpm.city="jamshedpur","Jharkhand",IF(_xlpm.city="bhilai","Chhattisgarh",IF(_xlpm.city="mumbai","Maharashtra",_xlpm.st))))) -> Haryana | AH25: =_xlfn.LET(_xlpm.d,PROPER(TRIM(tbl_FinancialData[[#This Row],[Department]])),IF(_xlpm.d="It","IT",_xlpm.d)) -> Operations | AI25: =_xlfn.LET(_xlpm.pid,tbl_FinancialData[[#This Row],[Product ID]],_xlpm.n,PROPER(TRIM(tbl_FinancialData[[#This Row],[Product Name]])),IF(_xlpm.pid="P020","Document Scanner",IF(_xlpm.pid="P015","Network Router",SUBSTITUTE(SUBSTITUTE(_xlpm.n,"Crm","CRM"),"Ups","UPS")))) -> Mouse | AJ25: =UPPER(TRIM(tbl_FinancialData[[#This Row],[Cost Center]])) -> CC-1005 | AL25: Blank City | AM25: =COUNTBLANK(tbl_FinancialData[Clean City]) -> 0 | AN25: =IF(AM25=0,"PASS","CHECK") -> PASS
A26: TXN-00025 | B26: 46104 | C26: March | D26: ="Q"&INT(MOD(MONTH(B26)-4,12)/3)+1 -> Q4 | E26: ="FY"& (YEAR(B26)+(MONTH(B26)>=4)) -> FY2026 | F26: West | G26: India | H26: Rajasthan | I26: Udaipur | J26: Branch A | K26: Marketing | L26: CC-1004 | M26: P018 | N26: Projector | O26: Electronics | P26: Presentation | Q26: 32676.06 | R26: 37255.12 | S26: 20090.81 | T26: 2257.52 | U26: 2260.85 | V26: 3241.23 | W26: 599.22 | X26: 28449.63 | Y26: 12585.25 | Z26: =Q26-X26 -> 4226.43 | AA26: =Z26/Q26 -> 0.12934332 | AB26: -4579.06 | AC26: 980.28 | AD26: 3803.49 | AE26: 35499.27 | AF26: =IF(tbl_FinancialData[[#This Row],[City]]="","Unknown",PROPER(TRIM(tbl_FinancialData[[#This Row],[City]]))) -> Udaipur | AG26: =_xlfn.LET(_xlpm.city,LOWER(TRIM(tbl_FinancialData[[#This Row],[City]])),_xlpm.st,PROPER(TRIM(tbl_FinancialData[[#This Row],[State]])),IF(_xlpm.city="pune","Maharashtra",IF(_xlpm.city="jamshedpur","Jharkhand",IF(_xlpm.city="bhilai","Chhattisgarh",IF(_xlpm.city="mumbai","Maharashtra",_xlpm.st))))) -> Rajasthan | AH26: =_xlfn.LET(_xlpm.d,PROPER(TRIM(tbl_FinancialData[[#This Row],[Department]])),IF(_xlpm.d="It","IT",_xlpm.d)) -> Marketing | AI26: =_xlfn.LET(_xlpm.pid,tbl_FinancialData[[#This Row],[Product ID]],_xlpm.n,PROPER(TRIM(tbl_FinancialData[[#This Row],[Product Name]])),IF(_xlpm.pid="P020","Document Scanner",IF(_xlpm.pid="P015","Network Router",SUBSTITUTE(SUBSTITUTE(_xlpm.n,"Crm","CRM"),"Ups","UPS")))) -> Projector | AJ26: =UPPER(TRIM(tbl_FinancialData[[#This Row],[Cost Center]])) -> CC-1004 | AL26: Blank State | AM26: =COUNTBLANK(tbl_FinancialData[State]) -> 0 | AN26: =IF(AM26=0,"PASS","CHECK") -> PASS
A27: TXN-00026 | B27: 45831 | C27: June | D27: ="Q"&INT(MOD(MONTH(B27)-4,12)/3)+1 -> Q1 | E27: ="FY"& (YEAR(B27)+(MONTH(B27)>=4)) -> FY2026 | F27: West | G27: India | H27: Gujarat | I27: Ahmedabad | J27: Branch C | K27: Sales | L27: CC-1004 | M27: P012 | N27: Accounting Software | O27: Software | P27: Business Software | Q27: 34032.17 | R27: 33571.77 | S27: 24150.33 | T27: 3544.16 | U27: 1918.18 | V27: 2703.59 | W27: 439.52 | X27: 32755.78 | Y27: 9881.85 | Z27: =Q27-X27 -> 1276.39 | AA27: =Z27/Q27 -> 0.037505396 | AB27: 460.4 | AC27: 0 | AD27: 6125.79 | AE27: 40157.96 | AF27: =IF(tbl_FinancialData[[#This Row],[City]]="","Unknown",PROPER(TRIM(tbl_FinancialData[[#This Row],[City]]))) -> Ahmedabad | AG27: =_xlfn.LET(_xlpm.city,LOWER(TRIM(tbl_FinancialData[[#This Row],[City]])),_xlpm.st,PROPER(TRIM(tbl_FinancialData[[#This Row],[State]])),IF(_xlpm.city="pune","Maharashtra",IF(_xlpm.city="jamshedpur","Jharkhand",IF(_xlpm.city="bhilai","Chhattisgarh",IF(_xlpm.city="mumbai","Maharashtra",_xlpm.st))))) -> Gujarat | AH27: =_xlfn.LET(_xlpm.d,PROPER(TRIM(tbl_FinancialData[[#This Row],[Department]])),IF(_xlpm.d="It","IT",_xlpm.d)) -> Sales | AI27: =_xlfn.LET(_xlpm.pid,tbl_FinancialData[[#This Row],[Product ID]],_xlpm.n,PROPER(TRIM(tbl_FinancialData[[#This Row],[Product Name]])),IF(_xlpm.pid="P020","Document Scanner",IF(_xlpm.pid="P015","Network Router",SUBSTITUTE(SUBSTITUTE(_xlpm.n,"Crm","CRM"),"Ups","UPS")))) -> Accounting Software | AJ27: =UPPER(TRIM(tbl_FinancialData[[#This Row],[Cost Center]])) -> CC-1004 | AL27: Blank Department | AM27: =COUNTBLANK(tbl_FinancialData[Department]) -> 0 | AN27: =IF(AM27=0,"PASS","CHECK") -> PASS
A28: TXN-00027 | B28: 45800 | C28: May | D28: ="Q"&INT(MOD(MONTH(B28)-4,12)/3)+1 -> Q1 | E28: ="FY"& (YEAR(B28)+(MONTH(B28)>=4)) -> FY2026 | F28: West | G28: India | H28: Maharashtra | I28: Nagpur | J28: Branch A | K28: IT | L28: CC-1002 | M28: P007 | N28: Tablet | O28: Electronics | P28: Mobile | Q28: 50779.14 | R28: 55913.45 | S28: 31027.06 | T28: 5406.28 | U28: 4466.65 | V28: 4826.17 | W28: 1995.3 | X28: 47721.47 | Y28: 19752.08 | Z28: =Q28-X28 -> 3057.67 | AA28: =Z28/Q28 -> 0.06021508 | AB28: -5134.31 | AC28: 4062.33 | AD28: 8409.03 | AE28: 55125.84 | AF28: =IF(tbl_FinancialData[[#This Row],[City]]="","Unknown",PROPER(TRIM(tbl_FinancialData[[#This Row],[City]]))) -> Nagpur | AG28: =_xlfn.LET(_xlpm.city,LOWER(TRIM(tbl_FinancialData[[#This Row],[City]])),_xlpm.st,PROPER(TRIM(tbl_FinancialData[[#This Row],[State]])),IF(_xlpm.city="pune","Maharashtra",IF(_xlpm.city="jamshedpur","Jharkhand",IF(_xlpm.city="bhilai","Chhattisgarh",IF(_xlpm.city="mumbai","Maharashtra",_xlpm.st))))) -> Maharashtra | AH28: =_xlfn.LET(_xlpm.d,PROPER(TRIM(tbl_FinancialData[[#This Row],[Department]])),IF(_xlpm.d="It","IT",_xlpm.d)) -> IT | AI28: =_xlfn.LET(_xlpm.pid,tbl_FinancialData[[#This Row],[Product ID]],_xlpm.n,PROPER(TRIM(tbl_FinancialData[[#This Row],[Product Name]])),IF(_xlpm.pid="P020","Document Scanner",IF(_xlpm.pid="P015","Network Router",SUBSTITUTE(SUBSTITUTE(_xlpm.n,"Crm","CRM"),"Ups","UPS")))) -> Tablet | AJ28: =UPPER(TRIM(tbl_FinancialData[[#This Row],[Cost Center]])) -> CC-1002 | AL28: Blank Product Name | AM28: =COUNTBLANK(tbl_FinancialData[Product Name]) -> 0 | AN28: =IF(AM28=0,"PASS","CHECK") -> PASS
A29: TXN-00028 | B29: 45921 | C29: September | D29: ="Q"&INT(MOD(MONTH(B29)-4,12)/3)+1 -> Q2 | E29: ="FY"& (YEAR(B29)+(MONTH(B29)>=4)) -> FY2026 | F29: West | G29: India | H29: Gujarat | I29: Ahmedabad | J29: Branch B | K29: IT | L29: CC-1002 | M29: P005 | N29: Office Desk | O29: Furniture | P29: Office Furniture | Q29: 17169.71 | R29: 18103.6 | S29: 11798.22 | T29: 2067.73 | U29: 693.39 | V29: 1933.58 | W29: 527.39 | X29: 17020.3 | Y29: 5371.49 | Z29: =Q29-X29 -> 149.41 | AA29: =Z29/Q29 -> 0.0087019524 | AB29: -933.89 | AC29: 515.09 | AD29: 2997.83 | AE29: 19652.45 | AF29: =IF(tbl_FinancialData[[#This Row],[City]]="","Unknown",PROPER(TRIM(tbl_FinancialData[[#This Row],[City]]))) -> Ahmedabad | AG29: =_xlfn.LET(_xlpm.city,LOWER(TRIM(tbl_FinancialData[[#This Row],[City]])),_xlpm.st,PROPER(TRIM(tbl_FinancialData[[#This Row],[State]])),IF(_xlpm.city="pune","Maharashtra",IF(_xlpm.city="jamshedpur","Jharkhand",IF(_xlpm.city="bhilai","Chhattisgarh",IF(_xlpm.city="mumbai","Maharashtra",_xlpm.st))))) -> Gujarat | AH29: =_xlfn.LET(_xlpm.d,PROPER(TRIM(tbl_FinancialData[[#This Row],[Department]])),IF(_xlpm.d="It","IT",_xlpm.d)) -> IT | AI29: =_xlfn.LET(_xlpm.pid,tbl_FinancialData[[#This Row],[Product ID]],_xlpm.n,PROPER(TRIM(tbl_FinancialData[[#This Row],[Product Name]])),IF(_xlpm.pid="P020","Document Scanner",IF(_xlpm.pid="P015","Network Router",SUBSTITUTE(SUBSTITUTE(_xlpm.n,"Crm","CRM"),"Ups","UPS")))) -> Office Desk | AJ29: =UPPER(TRIM(tbl_FinancialData[[#This Row],[Cost Center]])) -> CC-1002 | AL29: Blank Cost Center | AM29: =COUNTBLANK(tbl_FinancialData[Cost Center]) -> 0 | AN29: =IF(AM29=0,"PASS","CHECK") -> PASS
A30: TXN-00029 | B30: 46022 | C30: December | D30: ="Q"&INT(MOD(MONTH(B30)-4,12)/3)+1 -> Q3 | E30: ="FY"& (YEAR(B30)+(MONTH(B30)>=4)) -> FY2026 | F30: West | G30: India | H30: Gujarat | I30: Vadodara | J30: Branch C | K30: Sales | L30: CC-1003 | M30: P007 | N30: Tablet | O30: Electronics | P30: Mobile | Q30: 34662.19 | R30: 34716.29 | S30: 21391.89 | T30: 3787.81 | U30: 2595.08 | V30: 3668.07 | W30: 1249.48 | X30: 32692.33 | Y30: 13270.3 | Z30: =Q30-X30 -> 1969.86 | AA30: =Z30/Q30 -> 0.056830223 | AB30: -54.09 | AC30: 1733.11 | AD30: 1646.45 | AE30: 34575.54 | AF30: =IF(tbl_FinancialData[[#This Row],[City]]="","Unknown",PROPER(TRIM(tbl_FinancialData[[#This Row],[City]]))) -> Vadodara | AG30: =_xlfn.LET(_xlpm.city,LOWER(TRIM(tbl_FinancialData[[#This Row],[City]])),_xlpm.st,PROPER(TRIM(tbl_FinancialData[[#This Row],[State]])),IF(_xlpm.city="pune","Maharashtra",IF(_xlpm.city="jamshedpur","Jharkhand",IF(_xlpm.city="bhilai","Chhattisgarh",IF(_xlpm.city="mumbai","Maharashtra",_xlpm.st))))) -> Gujarat | AH30: =_xlfn.LET(_xlpm.d,PROPER(TRIM(tbl_FinancialData[[#This Row],[Department]])),IF(_xlpm.d="It","IT",_xlpm.d)) -> Sales | AI30: =_xlfn.LET(_xlpm.pid,tbl_FinancialData[[#This Row],[Product ID]],_xlpm.n,PROPER(TRIM(tbl_FinancialData[[#This Row],[Product Name]])),IF(_xlpm.pid="P020","Document Scanner",IF(_xlpm.pid="P015","Network Router",SUBSTITUTE(SUBSTITUTE(_xlpm.n,"Crm","CRM"),"Ups","UPS")))) -> Tablet | AJ30: =UPPER(TRIM(tbl_FinancialData[[#This Row],[Cost Center]])) -> CC-1003 | AL30: Invalid Profit Margin | AM30: =COUNTIF(tbl_FinancialData[Profit Margin %],">1")+COUNTIF(tbl_FinancialData[Profit Margin %],"<-1") -> 0 | AN30: =IF(AM30=0,"PASS","CHECK") -> PASS
A31: TXN-00030 | B31: 45938 | C31: October | D31: ="Q"&INT(MOD(MONTH(B31)-4,12)/3)+1 -> Q3 | E31: ="FY"& (YEAR(B31)+(MONTH(B31)>=4)) -> FY2026 | F31: East | G31: India | H31: West Bengal | I31: Kolkata | J31: Branch B | K31: Finance | L31: CC-1002 | M31: P012 | N31: Accounting Software | O31: Software | P31: Business Software | Q31: 29790.11 | R31: 29099.15 | S31: 14609.55 | T31: 3693.12 | U31: 2524.49 | V31: 1794.53 | W31: 1022.97 | X31: 23644.67 | Y31: 15180.56 | Z31: =Q31-X31 -> 6145.44 | AA31: =Z31/Q31 -> 0.20629128 | AB31: 690.95 | AC31: 0 | AD31: 1489.51 | AE31: 31279.61 | AF31: =IF(tbl_FinancialData[[#This Row],[City]]="","Unknown",PROPER(TRIM(tbl_FinancialData[[#This Row],[City]]))) -> Kolkata | AG31: =_xlfn.LET(_xlpm.city,LOWER(TRIM(tbl_FinancialData[[#This Row],[City]])),_xlpm.st,PROPER(TRIM(tbl_FinancialData[[#This Row],[State]])),IF(_xlpm.city="pune","Maharashtra",IF(_xlpm.city="jamshedpur","Jharkhand",IF(_xlpm.city="bhilai","Chhattisgarh",IF(_xlpm.city="mumbai","Maharashtra",_xlpm.st))))) -> West Bengal | AH31: =_xlfn.LET(_xlpm.d,PROPER(TRIM(tbl_FinancialData[[#This Row],[Department]])),IF(_xlpm.d="It","IT",_xlpm.d)) -> Finance | AI31: =_xlfn.LET(_xlpm.pid,tbl_FinancialData[[#This Row],[Product ID]],_xlpm.n,PROPER(TRIM(tbl_FinancialData[[#This Row],[Product Name]])),IF(_xlpm.pid="P020","Document Scanner",IF(_xlpm.pid="P015","Network Router",SUBSTITUTE(SUBSTITUTE(_xlpm.n,"Crm","CRM"),"Ups","UPS")))) -> Accounting Software | AJ31: =UPPER(TRIM(tbl_FinancialData[[#This Row],[Cost Center]])) -> CC-1002 | AL31: Negative Net Revenue | AM31: =COUNTIF(tbl_FinancialData[Net Revenue],"<0") -> 0 | AN31: =IF(AM31=0,"PASS","CHECK") -> PASS
A32: TXN-00031 | B32: 46052 | C32: January | D32: ="Q"&INT(MOD(MONTH(B32)-4,12)/3)+1 -> Q4 | E32: ="FY"& (YEAR(B32)+(MONTH(B32)>=4)) -> FY2026 | F32: West | G32: India | H32: Goa | I32: Panaji | J32: Branch A | K32: Operations | L32: CC-1003 | M32: P016 | N32: Network Switch | O32: Networking | P32: Network Equipment | Q32: 35907.04 | R32: 41925.45 | S32: 17734.03 | T32: 2928.64 | U32: 1146.84 | V32: 2400.49 | W32: 572.32 | X32: 24782.32 | Y32: 18173.01 | Z32: =Q32-X32 -> 11124.72 | AA32: =Z32/Q32 -> 0.30982002 | AB32: -6018.41 | AC32: 1795.35 | AD32: 4093.4 | AE32: 38205.1 | AF32: =IF(tbl_FinancialData[[#This Row],[City]]="","Unknown",PROPER(TRIM(tbl_FinancialData[[#This Row],[City]]))) -> Panaji | AG32: =_xlfn.LET(_xlpm.city,LOWER(TRIM(tbl_FinancialData[[#This Row],[City]])),_xlpm.st,PROPER(TRIM(tbl_FinancialData[[#This Row],[State]])),IF(_xlpm.city="pune","Maharashtra",IF(_xlpm.city="jamshedpur","Jharkhand",IF(_xlpm.city="bhilai","Chhattisgarh",IF(_xlpm.city="mumbai","Maharashtra",_xlpm.st))))) -> Goa | AH32: =_xlfn.LET(_xlpm.d,PROPER(TRIM(tbl_FinancialData[[#This Row],[Department]])),IF(_xlpm.d="It","IT",_xlpm.d)) -> Operations | AI32: =_xlfn.LET(_xlpm.pid,tbl_FinancialData[[#This Row],[Product ID]],_xlpm.n,PROPER(TRIM(tbl_FinancialData[[#This Row],[Product Name]])),IF(_xlpm.pid="P020","Document Scanner",IF(_xlpm.pid="P015","Network Router",SUBSTITUTE(SUBSTITUTE(_xlpm.n,"Crm","CRM"),"Ups","UPS")))) -> Network Switch | AJ32: =UPPER(TRIM(tbl_FinancialData[[#This Row],[Cost Center]])) -> CC-1003 | AL32: Negative Total Expense | AM32: =COUNTIF(tbl_FinancialData[Total Expense],"<0") -> 0 | AN32: =IF(AM32=0,"PASS","CHECK") -> PASS
A33: TXN-00032 | B33: 46063 | C33: February | D33: ="Q"&INT(MOD(MONTH(B33)-4,12)/3)+1 -> Q4 | E33: ="FY"& (YEAR(B33)+(MONTH(B33)>=4)) -> FY2026 | F33: West | G33: India | H33: Rajasthan | I33: Jaipur | J33: Branch A | K33: Sales | L33: CC-1003 | M33: P017 | N33: UPS System | O33: Electronics | P33: Power Equipment | Q33: 31046.84 | R33: 32935.56 | S33: 16921.46 | T33: 1883.14 | U33: 929.95 | V33: 3577.92 | W33: 763.2 | X33: 24075.66 | Y33: 14125.39 | Z33: =Q33-X33 -> 6971.18 | AA33: =Z33/Q33 -> 0.22453751 | AB33: -1888.72 | AC33: 1552.34 | AD33: 5309.01 | AE33: 34803.51 | AF33: =IF(tbl_FinancialData[[#This Row],[City]]="","Unknown",PROPER(TRIM(tbl_FinancialData[[#This Row],[City]]))) -> Jaipur | AG33: =_xlfn.LET(_xlpm.city,LOWER(TRIM(tbl_FinancialData[[#This Row],[City]])),_xlpm.st,PROPER(TRIM(tbl_FinancialData[[#This Row],[State]])),IF(_xlpm.city="pune","Maharashtra",IF(_xlpm.city="jamshedpur","Jharkhand",IF(_xlpm.city="bhilai","Chhattisgarh",IF(_xlpm.city="mumbai","Maharashtra",_xlpm.st))))) -> Rajasthan | AH33: =_xlfn.LET(_xlpm.d,PROPER(TRIM(tbl_FinancialData[[#This Row],[Department]])),IF(_xlpm.d="It","IT",_xlpm.d)) -> Sales | AI33: =_xlfn.LET(_xlpm.pid,tbl_FinancialData[[#This Row],[Product ID]],_xlpm.n,PROPER(TRIM(tbl_FinancialData[[#This Row],[Product Name]])),IF(_xlpm.pid="P020","Document Scanner",IF(_xlpm.pid="P015","Network Router",SUBSTITUTE(SUBSTITUTE(_xlpm.n,"Crm","CRM"),"Ups","UPS")))) -> UPS System | AJ33: =UPPER(TRIM(tbl_FinancialData[[#This Row],[Cost Center]])) -> CC-1003
A34: TXN-00033 | B34: 45757 | C34: April | D34: ="Q"&INT(MOD(MONTH(B34)-4,12)/3)+1 -> Q1 | E34: ="FY"& (YEAR(B34)+(MONTH(B34)>=4)) -> FY2026 | F34: Central | G34: India | H34: Chhattisgarh | I34: Bilaspur | J34: Branch A | K34: Sales | L34: CC-1001 | M34: P001 | N34: Business Laptop | O34: Electronics | P34: Computing | Q34: 54421.25 | R34: 54041.48 | S34: 35912.52 | T34: 4432.02 | U34: 4293.6 | V34: 4654.46 | W34: 665.19 | X34: 49957.78 | Y34: 18508.73 | Z34: =Q34-X34 -> 4463.47 | AA34: =Z34/Q34 -> 0.082017043 | AB34: 379.77 | AC34: 0 | AD34: 2721.06 | AE34: 57142.31 | AF34: =IF(tbl_FinancialData[[#This Row],[City]]="","Unknown",PROPER(TRIM(tbl_FinancialData[[#This Row],[City]]))) -> Bilaspur | AG34: =_xlfn.LET(_xlpm.city,LOWER(TRIM(tbl_FinancialData[[#This Row],[City]])),_xlpm.st,PROPER(TRIM(tbl_FinancialData[[#This Row],[State]])),IF(_xlpm.city="pune","Maharashtra",IF(_xlpm.city="jamshedpur","Jharkhand",IF(_xlpm.city="bhilai","Chhattisgarh",IF(_xlpm.city="mumbai","Maharashtra",_xlpm.st))))) -> Chhattisgarh | AH34: =_xlfn.LET(_xlpm.d,PROPER(TRIM(tbl_FinancialData[[#This Row],[Department]])),IF(_xlpm.d="It","IT",_xlpm.d)) -> Sales | AI34: =_xlfn.LET(_xlpm.pid,tbl_FinancialData[[#This Row],[Product ID]],_xlpm.n,PROPER(TRIM(tbl_FinancialData[[#This Row],[Product Name]])),IF(_xlpm.pid="P020","Document Scanner",IF(_xlpm.pid="P015","Network Router",SUBSTITUTE(SUBSTITUTE(_xlpm.n,"Crm","CRM"),"Ups","UPS")))) -> Business Laptop | AJ34: =UPPER(TRIM(tbl_FinancialData[[#This Row],[Cost Center]])) -> CC-1001
A35: TXN-00034 | B35: 46058 | C35: February | D35: ="Q"&INT(MOD(MONTH(B35)-4,12)/3)+1 -> Q4 | E35: ="FY"& (YEAR(B35)+(MONTH(B35)>=4)) -> FY2026 | F35: Central | G35: India | H35: Madhya Pradesh | I35: Bhopal | J35: Branch C | K35: Marketing | L35: CC-1003 | M35: P005 | N35: Office Desk | O35: Furniture | P35: Office Furniture | Q35: 28871.45 | R35: 28679.61 | S35: 15528.81 | T35: 1917.17 | U35: 1193.65 | V35: 1789.41 | W35: 498.12 | X35: 20927.16 | Y35: 13342.64 | Z35: =Q35-X35 -> 7944.29 | AA35: =Z35/Q35 -> 0.27516076 | AB35: 191.85 | AC35: 2309.72 | AD35: 4781.11 | AE35: 31342.85 | AF35: =IF(tbl_FinancialData[[#This Row],[City]]="","Unknown",PROPER(TRIM(tbl_FinancialData[[#This Row],[City]]))) -> Bhopal | AG35: =_xlfn.LET(_xlpm.city,LOWER(TRIM(tbl_FinancialData[[#This Row],[City]])),_xlpm.st,PROPER(TRIM(tbl_FinancialData[[#This Row],[State]])),IF(_xlpm.city="pune","Maharashtra",IF(_xlpm.city="jamshedpur","Jharkhand",IF(_xlpm.city="bhilai","Chhattisgarh",IF(_xlpm.city="mumbai","Maharashtra",_xlpm.st))))) -> Madhya Pradesh | AH35: =_xlfn.LET(_xlpm.d,PROPER(TRIM(tbl_FinancialData[[#This Row],[Department]])),IF(_xlpm.d="It","IT",_xlpm.d)) -> Marketing | AI35: =_xlfn.LET(_xlpm.pid,tbl_FinancialData[[#This Row],[Product ID]],_xlpm.n,PROPER(TRIM(tbl_FinancialData[[#This Row],[Product Name]])),IF(_xlpm.pid="P020","Document Scanner",IF(_xlpm.pid="P015","Network Router",SUBSTITUTE(SUBSTITUTE(_xlpm.n,"Crm","CRM"),"Ups","UPS")))) -> Office Desk | AJ35: =UPPER(TRIM(tbl_FinancialData[[#This Row],[Cost Center]])) -> CC-1003
A36: TXN-00035 | B36: 45781 | C36: May | D36: ="Q"&INT(MOD(MONTH(B36)-4,12)/3)+1 -> Q1 | E36: ="FY"& (YEAR(B36)+(MONTH(B36)>=4)) -> FY2026 | F36: South | G36: India | H36: Kerala | I36: Kozhikode | J36: Branch B | K36: Finance | L36: CC-1003 | M36: P018 | N36: Projector | O36: Electronics | P36: Presentation | Q36: 62763.15 | R36: 65793.44 | S36: 43331.48 | T36: 5164.07 | U36: 2115.81 | V36: 2655.05 | W36: 2286.45 | X36: 55552.85 | Y36: 19431.67 | Z36: =Q36-X36 -> 7210.3 | AA36: =Z36/Q36 -> 0.1148811 | AB36: -3030.29 | AC36: 3138.16 | AD36: 10732.5 | AE36: 70357.49 | AF36: =IF(tbl_FinancialData[[#This Row],[City]]="","Unknown",PROPER(TRIM(tbl_FinancialData[[#This Row],[City]]))) -> Kozhikode | AG36: =_xlfn.LET(_xlpm.city,LOWER(TRIM(tbl_FinancialData[[#This Row],[City]])),_xlpm.st,PROPER(TRIM(tbl_FinancialData[[#This Row],[State]])),IF(_xlpm.city="pune","Maharashtra",IF(_xlpm.city="jamshedpur","Jharkhand",IF(_xlpm.city="bhilai","Chhattisgarh",IF(_xlpm.city="mumbai","Maharashtra",_xlpm.st))))) -> Kerala | AH36: =_xlfn.LET(_xlpm.d,PROPER(TRIM(tbl_FinancialData[[#This Row],[Department]])),IF(_xlpm.d="It","IT",_xlpm.d)) -> Finance | AI36: =_xlfn.LET(_xlpm.pid,tbl_FinancialData[[#This Row],[Product ID]],_xlpm.n,PROPER(TRIM(tbl_FinancialData[[#This Row],[Product Name]])),IF(_xlpm.pid="P020","Document Scanner",IF(_xlpm.pid="P015","Network Router",SUBSTITUTE(SUBSTITUTE(_xlpm.n,"Crm","CRM"),"Ups","UPS")))) -> Projector | AJ36: =UPPER(TRIM(tbl_FinancialData[[#This Row],[Cost Center]])) -> CC-1003
A37: TXN-00036 | B37: 45850 | C37: July | D37: ="Q"&INT(MOD(MONTH(B37)-4,12)/3)+1 -> Q2 | E37: ="FY"& (YEAR(B37)+(MONTH(B37)>=4)) -> FY2026 | F37: North | G37: India | H37: Uttar Pradesh | I37: Kanpur | J37: Branch B | K37: Operations | L37: CC-1002 | M37: P015 | N37: Network Router | O37: Networking | P37: Network Equipment | Q37: 24879.63 | R37: 24493.41 | S37: 15011.31 | T37: 2803.74 | U37: 1263.27 | V37: 2233.37 | W37: 999.73 | X37: 22311.42 | Y37: 9868.32 | Z37: =Q37-X37 -> 2568.21 | AA37: =Z37/Q37 -> 0.10322541 | AB37: 386.22 | AC37: 2487.96 | AD37: 1119.58 | AE37: 23511.25 | AF37: =IF(tbl_FinancialData[[#This Row],[City]]="","Unknown",PROPER(TRIM(tbl_FinancialData[[#This Row],[City]]))) -> Kanpur | AG37: =_xlfn.LET(_xlpm.city,LOWER(TRIM(tbl_FinancialData[[#This Row],[City]])),_xlpm.st,PROPER(TRIM(tbl_FinancialData[[#This Row],[State]])),IF(_xlpm.city="pune","Maharashtra",IF(_xlpm.city="jamshedpur","Jharkhand",IF(_xlpm.city="bhilai","Chhattisgarh",IF(_xlpm.city="mumbai","Maharashtra",_xlpm.st))))) -> Uttar Pradesh | AH37: =_xlfn.LET(_xlpm.d,PROPER(TRIM(tbl_FinancialData[[#This Row],[Department]])),IF(_xlpm.d="It","IT",_xlpm.d)) -> Operations | AI37: =_xlfn.LET(_xlpm.pid,tbl_FinancialData[[#This Row],[Product ID]],_xlpm.n,PROPER(TRIM(tbl_FinancialData[[#This Row],[Product Name]])),IF(_xlpm.pid="P020","Document Scanner",IF(_xlpm.pid="P015","Network Router",SUBSTITUTE(SUBSTITUTE(_xlpm.n,"Crm","CRM"),"Ups","UPS")))) -> Network Router | AJ37: =UPPER(TRIM(tbl_FinancialData[[#This Row],[Cost Center]])) -> CC-1002
A38: TXN-00037 | B38: 45931 | C38: October | D38: ="Q"&INT(MOD(MONTH(B38)-4,12)/3)+1 -> Q3 | E38: ="FY"& (YEAR(B38)+(MONTH(B38)>=4)) -> FY2026 | F38: West | G38: India | H38: Maharashtra | I38: Mumbai | J38: Branch B | K38: Operations | L38: CC-1002 | M38: P013 | N38: CRM Software | O38: Software | P38: Business Software | Q38: 10769.33 | R38: 10580.53 | S38: 6557.91 | T38: 934.88 | U38: 678.57 | V38: 775.65 | W38: 370.66 | X38: 9317.68 | Y38: 4211.42 | Z38: =Q38-X38 -> 1451.65 | AA38: =Z38/Q38 -> 0.13479483 | AB38: 188.8 | AC38: 215.39 | AD38: 1899.71 | AE38: 12453.65 | AF38: =IF(tbl_FinancialData[[#This Row],[City]]="","Unknown",PROPER(TRIM(tbl_FinancialData[[#This Row],[City]]))) -> Mumbai | AG38: =_xlfn.LET(_xlpm.city,LOWER(TRIM(tbl_FinancialData[[#This Row],[City]])),_xlpm.st,PROPER(TRIM(tbl_FinancialData[[#This Row],[State]])),IF(_xlpm.city="pune","Maharashtra",IF(_xlpm.city="jamshedpur","Jharkhand",IF(_xlpm.city="bhilai","Chhattisgarh",IF(_xlpm.city="mumbai","Maharashtra",_xlpm.st))))) -> Maharashtra | AH38: =_xlfn.LET(_xlpm.d,PROPER(TRIM(tbl_FinancialData[[#This Row],[Department]])),IF(_xlpm.d="It","IT",_xlpm.d)) -> Operations | AI38: =_xlfn.LET(_xlpm.pid,tbl_FinancialData[[#This Row],[Product ID]],_xlpm.n,PROPER(TRIM(tbl_FinancialData[[#This Row],[Product Name]])),IF(_xlpm.pid="P020","Document Scanner",IF(_xlpm.pid="P015","Network Router",SUBSTITUTE(SUBSTITUTE(_xlpm.n,"Crm","CRM"),"Ups","UPS")))) -> CRM Software | AJ38: =UPPER(TRIM(tbl_FinancialData[[#This Row],[Cost Center]])) -> CC-1002
A39: TXN-00038 | B39: 46028 | C39: January | D39: ="Q"&INT(MOD(MONTH(B39)-4,12)/3)+1 -> Q4 | E39: ="FY"& (YEAR(B39)+(MONTH(B39)>=4)) -> FY2026 | F39: Central | G39: India | H39: Uttar Pradesh | I39: Agra | J39: Branch A | K39: IT | L39: CC-1005 | M39: P019 | N39: Conference Camera | O39: Electronics | P39: Video Conferencing | Q39: 16959.81 | R39: 16342.09 | S39: 8861.21 | T39: 968.34 | U39: 556.98 | V39: 1303.57 | W39: 292.08 | X39: 11982.18 | Y39: 8098.61 | Z39: =Q39-X39 -> 4977.63 | AA39: =Z39/Q39 -> 0.29349562 | AB39: 617.73 | AC39: 508.79 | AD39: 1974.12 | AE39: 18425.14 | AF39: =IF(tbl_FinancialData[[#This Row],[City]]="","Unknown",PROPER(TRIM(tbl_FinancialData[[#This Row],[City]]))) -> Agra | AG39: =_xlfn.LET(_xlpm.city,LOWER(TRIM(tbl_FinancialData[[#This Row],[City]])),_xlpm.st,PROPER(TRIM(tbl_FinancialData[[#This Row],[State]])),IF(_xlpm.city="pune","Maharashtra",IF(_xlpm.city="jamshedpur","Jharkhand",IF(_xlpm.city="bhilai","Chhattisgarh",IF(_xlpm.city="mumbai","Maharashtra",_xlpm.st))))) -> Uttar Pradesh | AH39: =_xlfn.LET(_xlpm.d,PROPER(TRIM(tbl_FinancialData[[#This Row],[Department]])),IF(_xlpm.d="It","IT",_xlpm.d)) -> IT | AI39: =_xlfn.LET(_xlpm.pid,tbl_FinancialData[[#This Row],[Product ID]],_xlpm.n,PROPER(TRIM(tbl_FinancialData[[#This Row],[Product Name]])),IF(_xlpm.pid="P020","Document Scanner",IF(_xlpm.pid="P015","Network Router",SUBSTITUTE(SUBSTITUTE(_xlpm.n,"Crm","CRM"),"Ups","UPS")))) -> Conference Camera | AJ39: =UPPER(TRIM(tbl_FinancialData[[#This Row],[Cost Center]])) -> CC-1005
A40: TXN-00039 | B40: 46048 | C40: January | D40: ="Q"&INT(MOD(MONTH(B40)-4,12)/3)+1 -> Q4 | E40: ="FY"& (YEAR(B40)+(MONTH(B40)>=4)) -> FY2026 | F40: South | G40: India | H40: Tamil Nadu | I40: Chennai | J40: Branch C | K40: Operations | L40: CC-1003 | M40: P016 | N40: Network Switch | O40: Networking | P40: Network Equipment | Q40: 7979.63 | R40: 8952.03 | S40: 5263.22 | T40: 516.77 | U40: 308.08 | V40: 555.68 | W40: 215.12 | X40: 6858.87 | Y40: 2716.41 | Z40: =Q40-X40 -> 1120.76 | AA40: =Z40/Q40 -> 0.14045263 | AB40: -972.4 | AC40: 398.98 | AD40: 909.68 | AE40: 8490.33 | AF40: =IF(tbl_FinancialData[[#This Row],[City]]="","Unknown",PROPER(TRIM(tbl_FinancialData[[#This Row],[City]]))) -> Chennai | AG40: =_xlfn.LET(_xlpm.city,LOWER(TRIM(tbl_FinancialData[[#This Row],[City]])),_xlpm.st,PROPER(TRIM(tbl_FinancialData[[#This Row],[State]])),IF(_xlpm.city="pune","Maharashtra",IF(_xlpm.city="jamshedpur","Jharkhand",IF(_xlpm.city="bhilai","Chhattisgarh",IF(_xlpm.city="mumbai","Maharashtra",_xlpm.st))))) -> Tamil Nadu | AH40: =_xlfn.LET(_xlpm.d,PROPER(TRIM(tbl_FinancialData[[#This Row],[Department]])),IF(_xlpm.d="It","IT",_xlpm.d)) -> Operations | AI40: =_xlfn.LET(_xlpm.pid,tbl_FinancialData[[#This Row],[Product ID]],_xlpm.n,PROPER(TRIM(tbl_FinancialData[[#This Row],[Product Name]])),IF(_xlpm.pid="P020","Document Scanner",IF(_xlpm.pid="P015","Network Router",SUBSTITUTE(SUBSTITUTE(_xlpm.n,"Crm","CRM"),"Ups","UPS")))) -> Network Switch | AJ40: =UPPER(TRIM(tbl_FinancialData[[#This Row],[Cost Center]])) -> CC-1003
A41: TXN-00040 | B41: 45963 | C41: November | D41: ="Q"&INT(MOD(MONTH(B41)-4,12)/3)+1 -> Q3 | E41: ="FY"& (YEAR(B41)+(MONTH(B41)>=4)) -> FY2026 | F41: West | G41: India | H41: Gujarat | I41: Surat | J41: Branch C | K41: Sales | L41: CC-1003 | M41: P015 | N41: Network Router | O41: Networking | P41: Network Equipment | Q41: 36766.15 | R41: 32690.32 | S41: 25299.95 | T41: 2879.96 | U41: 1868.3 | V41: 1779.1 | W41: 1316.57 | X41: 33143.86 | Y41: 11466.2 | Z41: =Q41-X41 -> 3622.29 | AA41: =Z41/Q41 -> 0.098522418 | AB41: 4075.83 | AC41: 735.32 | AD41: 4323.7 | AE41: 40354.53 | AF41: =IF(tbl_FinancialData[[#This Row],[City]]="","Unknown",PROPER(TRIM(tbl_FinancialData[[#This Row],[City]]))) -> Surat | AG41: =_xlfn.LET(_xlpm.city,LOWER(TRIM(tbl_FinancialData[[#This Row],[City]])),_xlpm.st,PROPER(TRIM(tbl_FinancialData[[#This Row],[State]])),IF(_xlpm.city="pune","Maharashtra",IF(_xlpm.city="jamshedpur","Jharkhand",IF(_xlpm.city="bhilai","Chhattisgarh",IF(_xlpm.city="mumbai","Maharashtra",_xlpm.st))))) -> Gujarat | AH41: =_xlfn.LET(_xlpm.d,PROPER(TRIM(tbl_FinancialData[[#This Row],[Department]])),IF(_xlpm.d="It","IT",_xlpm.d)) -> Sales | AI41: =_xlfn.LET(_xlpm.pid,tbl_FinancialData[[#This Row],[Product ID]],_xlpm.n,PROPER(TRIM(tbl_FinancialData[[#This Row],[Product Name]])),IF(_xlpm.pid="P020","Document Scanner",IF(_xlpm.pid="P015","Network Router",SUBSTITUTE(SUBSTITUTE(_xlpm.n,"Crm","CRM"),"Ups","UPS")))) -> Network Router | AJ41: =UPPER(TRIM(tbl_FinancialData[[#This Row],[Cost Center]])) -> CC-1003
A42: TXN-00041 | B42: 46020 | C42: December | D42: ="Q"&INT(MOD(MONTH(B42)-4,12)/3)+1 -> Q3 | E42: ="FY"& (YEAR(B42)+(MONTH(B42)>=4)) -> FY2026 | F42: South | G42: India | H42: Tamil Nadu | I42: Coimbatore | J42: Branch D | K42: Sales | L42: CC-1005 | M42: P020 | N42: Document Scanner | O42: Electronics | P42: Office Equipment | Q42: 38788.87 | R42: 41684.34 | S42: 23083.25 | T42: 3752.28 | U42: 2827.46 | V42: 3282.29 | W42: 1184.18 | X42: 34129.45 | Y42: 15705.63 | Z42: =Q42-X42 -> 4659.42 | AA42: =Z42/Q42 -> 0.1201226 | AB42: -2895.47 | AC42: 1939.44 | AD42: 4421.93 | AE42: 41271.36 | AF42: =IF(tbl_FinancialData[[#This Row],[City]]="","Unknown",PROPER(TRIM(tbl_FinancialData[[#This Row],[City]]))) -> Coimbatore | AG42: =_xlfn.LET(_xlpm.city,LOWER(TRIM(tbl_FinancialData[[#This Row],[City]])),_xlpm.st,PROPER(TRIM(tbl_FinancialData[[#This Row],[State]])),IF(_xlpm.city="pune","Maharashtra",IF(_xlpm.city="jamshedpur","Jharkhand",IF(_xlpm.city="bhilai","Chhattisgarh",IF(_xlpm.city="mumbai","Maharashtra",_xlpm.st))))) -> Tamil Nadu | AH42: =_xlfn.LET(_xlpm.d,PROPER(TRIM(tbl_FinancialData[[#This Row],[Department]])),IF(_xlpm.d="It","IT",_xlpm.d)) -> Sales | AI42: =_xlfn.LET(_xlpm.pid,tbl_FinancialData[[#This Row],[Product ID]],_xlpm.n,PROPER(TRIM(tbl_FinancialData[[#This Row],[Product Name]])),IF(_xlpm.pid="P020","Document Scanner",IF(_xlpm.pid="P015","Network Router",SUBSTITUTE(SUBSTITUTE(_xlpm.n,"Crm","CRM"),"Ups","UPS")))) -> Document Scanner | AJ42: =UPPER(TRIM(tbl_FinancialData[[#This Row],[Cost Center]])) -> CC-1005
A43: TXN-00042 | B43: 45848 | C43: July | D43: ="Q"&INT(MOD(MONTH(B43)-4,12)/3)+1 -> Q2 | E43: ="FY"& (YEAR(B43)+(MONTH(B43)>=4)) -> FY2026 | F43: South | G43: India | H43: Tamil Nadu | I43: Coimbatore | J43: Branch C | K43: Sales | L43: CC-1005 | M43: P006 | N43: Smartphone | O43: Electronics | P43: Mobile | Q43: 41468.12 | R43: 37758.17 | S43: 21426.01 | T43: 2889.36 | U43: 1469.81 | V43: 2277.65 | W43: 828.46 | X43: 28891.29 | Y43: 20042.12 | Z43: =Q43-X43 -> 12576.83 | AA43: =Z43/Q43 -> 0.30328913 | AB43: 3709.96 | AC43: 0 | AD43: 7464.26 | AE43: 48932.38 | AF43: =IF(tbl_FinancialData[[#This Row],[City]]="","Unknown",PROPER(TRIM(tbl_FinancialData[[#This Row],[City]]))) -> Coimbatore | AG43: =_xlfn.LET(_xlpm.city,LOWER(TRIM(tbl_FinancialData[[#This Row],[City]])),_xlpm.st,PROPER(TRIM(tbl_FinancialData[[#This Row],[State]])),IF(_xlpm.city="pune","Maharashtra",IF(_xlpm.city="jamshedpur","Jharkhand",IF(_xlpm.city="bhilai","Chhattisgarh",IF(_xlpm.city="mumbai","Maharashtra",_xlpm.st))))) -> Tamil Nadu | AH43: =_xlfn.LET(_xlpm.d,PROPER(TRIM(tbl_FinancialData[[#This Row],[Department]])),IF(_xlpm.d="It","IT",_xlpm.d)) -> Sales | AI43: =_xlfn.LET(_xlpm.pid,tbl_FinancialData[[#This Row],[Product ID]],_xlpm.n,PROPER(TRIM(tbl_FinancialData[[#This Row],[Product Name]])),IF(_xlpm.pid="P020","Document Scanner",IF(_xlpm.pid="P015","Network Router",SUBSTITUTE(SUBSTITUTE(_xlpm.n,"Crm","CRM"),"Ups","UPS")))) -> Smartphone | AJ43: =UPPER(TRIM(tbl_FinancialData[[#This Row],[Cost Center]])) -> CC-1005
A44: TXN-00043 | B44: 45994 | C44: December | D44: ="Q"&INT(MOD(MONTH(B44)-4,12)/3)+1 -> Q3 | E44: ="FY"& (YEAR(B44)+(MONTH(B44)>=4)) -> FY2026 | F44: North | G44: India | H44: Haryana | I44: Gurugram | J44: Branch D | K44: IT | L44: CC-1002 | M44: P020 | N44: Document Scanner | O44: Electronics | P44: Office Equipment | Q44: 80683.47 | R44: 90778.71 | S44: 43722.1 | T44: 5137.2 | U44: 5523.74 | V44: 9226.16 | W44: 2379.09 | X44: 65988.29 | Y44: 36961.36 | Z44: =Q44-X44 -> 14695.18 | AA44: =Z44/Q44 -> 0.18213371 | AB44: -10095.25 | AC44: 4034.17 | AD44: 9197.92 | AE44: 85847.21 | AF44: =IF(tbl_FinancialData[[#This Row],[City]]="","Unknown",PROPER(TRIM(tbl_FinancialData[[#This Row],[City]]))) -> Gurugram | AG44: =_xlfn.LET(_xlpm.city,LOWER(TRIM(tbl_FinancialData[[#This Row],[City]])),_xlpm.st,PROPER(TRIM(tbl_FinancialData[[#This Row],[State]])),IF(_xlpm.city="pune","Maharashtra",IF(_xlpm.city="jamshedpur","Jharkhand",IF(_xlpm.city="bhilai","Chhattisgarh",IF(_xlpm.city="mumbai","Maharashtra",_xlpm.st))))) -> Haryana | AH44: =_xlfn.LET(_xlpm.d,PROPER(TRIM(tbl_FinancialData[[#This Row],[Department]])),IF(_xlpm.d="It","IT",_xlpm.d)) -> IT | AI44: =_xlfn.LET(_xlpm.pid,tbl_FinancialData[[#This Row],[Product ID]],_xlpm.n,PROPER(TRIM(tbl_FinancialData[[#This Row],[Product Name]])),IF(_xlpm.pid="P020","Document Scanner",IF(_xlpm.pid="P015","Network Router",SUBSTITUTE(SUBSTITUTE(_xlpm.n,"Crm","CRM"),"Ups","UPS")))) -> Document Scanner | AJ44: =UPPER(TRIM(tbl_FinancialData[[#This Row],[Cost Center]])) -> CC-1002
... A206: TXN-00205 | B206: 45776 | C206: April | D206: ="Q"&INT(MOD(MONTH(B206)-4,12)/3)+1 -> Q1 | E206: ="FY"& (YEAR(B206)+(MONTH(B206)>=4)) -> FY2026 | F206: West | G206: India | H206: Rajasthan | I206: Jodhpur | J206: Branch D | K206: IT | L206: CC-1004 | M206: P009 | N206: Keyboard | O206: Accessories | P206: Computer Accessories | Q206: 6731.64 | R206: 7582.63 | S206: 4593.66 | T206: 597.82 | U206: 314.27 | V206: 695.54 | W206: 173.64 | X206: 6374.94 | Y206: 2137.98 | Z206: =Q206-X206 -> 356.7 | AA206: =Z206/Q206 -> 0.052988573 | AB206: -850.99 | AC206: 134.63 | AD206: 1187.46 | AE206: 7784.46 | AF206: =IF(tbl_FinancialData[[#This Row],[City]]="","Unknown",PROPER(TRIM(tbl_FinancialData[[#This Row],[City]]))) -> Jodhpur | AG206: =_xlfn.LET(_xlpm.city,LOWER(TRIM(tbl_FinancialData[[#This Row],[City]])),_xlpm.st,PROPER(TRIM(tbl_FinancialData[[#This Row],[State]])),IF(_xlpm.city="pune","Maharashtra",IF(_xlpm.city="jamshedpur","Jharkhand",IF(_xlpm.city="bhilai","Chhattisgarh",IF(_xlpm.city="mumbai","Maharashtra",_xlpm.st))))) -> Rajasthan | AH206: =_xlfn.LET(_xlpm.d,PROPER(TRIM(tbl_FinancialData[[#This Row],[Department]])),IF(_xlpm.d="It","IT",_xlpm.d)) -> IT | AI206: =_xlfn.LET(_xlpm.pid,tbl_FinancialData[[#This Row],[Product ID]],_xlpm.n,PROPER(TRIM(tbl_FinancialData[[#This Row],[Product Name]])),IF(_xlpm.pid="P020","Document Scanner",IF(_xlpm.pid="P015","Network Router",SUBSTITUTE(SUBSTITUTE(_xlpm.n,"Crm","CRM"),"Ups","UPS")))) -> Keyboard | AJ206: =UPPER(TRIM(tbl_FinancialData[[#This Row],[Cost Center]])) -> CC-1004
A207: TXN-00206 | B207: 46018 | C207: December | D207: ="Q"&INT(MOD(MONTH(B207)-4,12)/3)+1 -> Q3 | E207: ="FY"& (YEAR(B207)+(MONTH(B207)>=4)) -> FY2026 | F207: East | G207: India | H207: West Bengal | J207: Branch B | K207: Operations | L207: CC-1002 | M207: P019 | N207: Conference Camera | O207: Electronics | P207: Video Conferencing | Q207: 27294.21 | R207: 24362.7 | S207: 16240.67 | T207: 1761.51 | U207: 2000.67 | V207: 2943.25 | W207: 794.14 | X207: 23740.24 | Y207: 11053.54 | Z207: =Q207-X207 -> 3553.97 | AA207: =Z207/Q207 -> 0.13020967 | AB207: 2931.52 | AC207: 2729.42 | AD207: 2947.78 | AE207: 27512.57 | AF207: =IF(tbl_FinancialData[[#This Row],[City]]="","Unknown",PROPER(TRIM(tbl_FinancialData[[#This Row],[City]]))) -> Unknown | AG207: =_xlfn.LET(_xlpm.city,LOWER(TRIM(tbl_FinancialData[[#This Row],[City]])),_xlpm.st,PROPER(TRIM(tbl_FinancialData[[#This Row],[State]])),IF(_xlpm.city="pune","Maharashtra",IF(_xlpm.city="jamshedpur","Jharkhand",IF(_xlpm.city="bhilai","Chhattisgarh",IF(_xlpm.city="mumbai","Maharashtra",_xlpm.st))))) -> West Bengal | AH207: =_xlfn.LET(_xlpm.d,PROPER(TRIM(tbl_FinancialData[[#This Row],[Department]])),IF(_xlpm.d="It","IT",_xlpm.d)) -> Operations | AI207: =_xlfn.LET(_xlpm.pid,tbl_FinancialData[[#This Row],[Product ID]],_xlpm.n,PROPER(TRIM(tbl_FinancialData[[#This Row],[Product Name]])),IF(_xlpm.pid="P020","Document Scanner",IF(_xlpm.pid="P015","Network Router",SUBSTITUTE(SUBSTITUTE(_xlpm.n,"Crm","CRM"),"Ups","UPS")))) -> Conference Camera | AJ207: =UPPER(TRIM(tbl_FinancialData[[#This Row],[Cost Center]])) -> CC-1002
A208: TXN-00207 | B208: 46080 | C208: February | D208: ="Q"&INT(MOD(MONTH(B208)-4,12)/3)+1 -> Q4 | E208: ="FY"& (YEAR(B208)+(MONTH(B208)>=4)) -> FY2026 | F208: West | G208: India | H208: Goa | I208: Panaji | J208: Branch C | K208: Sales | L208: CC-1003 | M208: P019 | N208: Conference Camera | O208: Electronics | P208: Video Conferencing | Q208: 25282.94 | R208: 26863.7 | S208: 16423.6 | T208: 2021.58 | U208: 1239.28 | V208: 1102.98 | W208: 562.5 | X208: 21349.94 | Y208: 8859.34 | Z208: =Q208-X208 -> 3933 | AA208: =Z208/Q208 -> 0.15555944 | AB208: -1580.76 | AC208: 2022.64 | AD208: 2791.24 | AE208: 26051.54 | AF208: =IF(tbl_FinancialData[[#This Row],[City]]="","Unknown",PROPER(TRIM(tbl_FinancialData[[#This Row],[City]]))) -> Panaji | AG208: =_xlfn.LET(_xlpm.city,LOWER(TRIM(tbl_FinancialData[[#This Row],[City]])),_xlpm.st,PROPER(TRIM(tbl_FinancialData[[#This Row],[State]])),IF(_xlpm.city="pune","Maharashtra",IF(_xlpm.city="jamshedpur","Jharkhand",IF(_xlpm.city="bhilai","Chhattisgarh",IF(_xlpm.city="mumbai","Maharashtra",_xlpm.st))))) -> Goa | AH208: =_xlfn.LET(_xlpm.d,PROPER(TRIM(tbl_FinancialData[[#This Row],[Department]])),IF(_xlpm.d="It","IT",_xlpm.d)) -> Sales | AI208: =_xlfn.LET(_xlpm.pid,tbl_FinancialData[[#This Row],[Product ID]],_xlpm.n,PROPER(TRIM(tbl_FinancialData[[#This Row],[Product Name]])),IF(_xlpm.pid="P020","Document Scanner",IF(_xlpm.pid="P015","Network Router",SUBSTITUTE(SUBSTITUTE(_xlpm.n,"Crm","CRM"),"Ups","UPS")))) -> Conference Camera | AJ208: =UPPER(TRIM(tbl_FinancialData[[#This Row],[Cost Center]])) -> CC-1003
A209: TXN-00208 | B209: 45809 | C209: June | D209: ="Q"&INT(MOD(MONTH(B209)-4,12)/3)+1 -> Q1 | E209: ="FY"& (YEAR(B209)+(MONTH(B209)>=4)) -> FY2026 | F209: West | G209: India | H209: Maharashtra | I209: Nagpur | J209: Branch D | K209: Sales | L209: CC-1001 | M209: P004 | N209: Office Chair | O209: Furniture | P209: Office Furniture | Q209: 27355.34 | R209: 30489.93 | S209: 18065.99 | T209: 3125.08 | U209: 1604.95 | V209: 1401.3 | W209: 916.14 | X209: 25113.47 | Y209: 9289.35 | Z209: =Q209-X209 -> 2241.87 | AA209: =Z209/Q209 -> 0.081953651 | AB209: -3134.59 | AC209: 1367.77 | AD209: 4677.76 | AE209: 30665.33 | AF209: =IF(tbl_FinancialData[[#This Row],[City]]="","Unknown",PROPER(TRIM(tbl_FinancialData[[#This Row],[City]]))) -> Nagpur | AG209: =_xlfn.LET(_xlpm.city,LOWER(TRIM(tbl_FinancialData[[#This Row],[City]])),_xlpm.st,PROPER(TRIM(tbl_FinancialData[[#This Row],[State]])),IF(_xlpm.city="pune","Maharashtra",IF(_xlpm.city="jamshedpur","Jharkhand",IF(_xlpm.city="bhilai","Chhattisgarh",IF(_xlpm.city="mumbai","Maharashtra",_xlpm.st))))) -> Maharashtra | AH209: =_xlfn.LET(_xlpm.d,PROPER(TRIM(tbl_FinancialData[[#This Row],[Department]])),IF(_xlpm.d="It","IT",_xlpm.d)) -> Sales | AI209: =_xlfn.LET(_xlpm.pid,tbl_FinancialData[[#This Row],[Product ID]],_xlpm.n,PROPER(TRIM(tbl_FinancialData[[#This Row],[Product Name]])),IF(_xlpm.pid="P020","Document Scanner",IF(_xlpm.pid="P015","Network Router",SUBSTITUTE(SUBSTITUTE(_xlpm.n,"Crm","CRM"),"Ups","UPS")))) -> Office Chair | AJ209: =UPPER(TRIM(tbl_FinancialData[[#This Row],[Cost Center]])) -> CC-1001
A210: TXN-00209 | B210: 45818 | C210: June | D210: ="Q"&INT(MOD(MONTH(B210)-4,12)/3)+1 -> Q1 | E210: ="FY"& (YEAR(B210)+(MONTH(B210)>=4)) -> FY2026 | F210: West | G210: India | H210: Goa | I210: Margao | J210: Branch A | K210: Sales | L210: CC-1003 | M210: P004 | N210: Office Chair | O210: Furniture | P210: Office Furniture | Q210: 28763.31 | R210: 31854.79 | S210: 15925.01 | T210: 2393.04 | U210: 2051.7 | V210: 2039.23 | W210: 880.09 | X210: 23289.08 | Y210: 12838.3 | Z210: =Q210-X210 -> 5474.23 | AA210: =Z210/Q210 -> 0.19031989 | AB210: -3091.49 | AC210: 575.27 | AD210: 3382.57 | AE210: 31570.61 | AF210: =IF(tbl_FinancialData[[#This Row],[City]]="","Unknown",PROPER(TRIM(tbl_FinancialData[[#This Row],[City]]))) -> Margao | AG210: =_xlfn.LET(_xlpm.city,LOWER(TRIM(tbl_FinancialData[[#This Row],[City]])),_xlpm.st,PROPER(TRIM(tbl_FinancialData[[#This Row],[State]])),IF(_xlpm.city="pune","Maharashtra",IF(_xlpm.city="jamshedpur","Jharkhand",IF(_xlpm.city="bhilai","Chhattisgarh",IF(_xlpm.city="mumbai","Maharashtra",_xlpm.st))))) -> Goa | AH210: =_xlfn.LET(_xlpm.d,PROPER(TRIM(tbl_FinancialData[[#This Row],[Department]])),IF(_xlpm.d="It","IT",_xlpm.d)) -> Sales | AI210: =_xlfn.LET(_xlpm.pid,tbl_FinancialData[[#This Row],[Product ID]],_xlpm.n,PROPER(TRIM(tbl_FinancialData[[#This Row],[Product Name]])),IF(_xlpm.pid="P020","Document Scanner",IF(_xlpm.pid="P015","Network Router",SUBSTITUTE(SUBSTITUTE(_xlpm.n,"Crm","CRM"),"Ups","UPS")))) -> Office Chair | AJ210: =UPPER(TRIM(tbl_FinancialData[[#This Row],[Cost Center]])) -> CC-1003
A211: TXN-00210 | B211: 45841 | C211: July | D211: ="Q"&INT(MOD(MONTH(B211)-4,12)/3)+1 -> Q2 | E211: ="FY"& (YEAR(B211)+(MONTH(B211)>=4)) -> FY2026 | F211: Central | G211: India | H211: Chhattisgarh | I211: Bilaspur | J211: Branch C | K211: Operations | L211: CC-1002 | M211: P002 | N211: Monitor | O211: Electronics | P211: Computing | Q211: 24677.74 | R211: 25053.66 | S211: 17522.17 | T211: 2084.95 | U211: 1498.12 | V211: 2039.87 | W211: 796.76 | X211: 23941.87 | Y211: 7155.57 | Z211: =Q211-X211 -> 735.87 | AA211: =Z211/Q211 -> 0.029819181 | AB211: -375.91 | AC211: 1233.89 | AD211: 1172.19 | AE211: 24616.05 | AF211: =IF(tbl_FinancialData[[#This Row],[City]]="","Unknown",PROPER(TRIM(tbl_FinancialData[[#This Row],[City]]))) -> Bilaspur | AG211: =_xlfn.LET(_xlpm.city,LOWER(TRIM(tbl_FinancialData[[#This Row],[City]])),_xlpm.st,PROPER(TRIM(tbl_FinancialData[[#This Row],[State]])),IF(_xlpm.city="pune","Maharashtra",IF(_xlpm.city="jamshedpur","Jharkhand",IF(_xlpm.city="bhilai","Chhattisgarh",IF(_xlpm.city="mumbai","Maharashtra",_xlpm.st))))) -> Chhattisgarh | AH211: =_xlfn.LET(_xlpm.d,PROPER(TRIM(tbl_FinancialData[[#This Row],[Department]])),IF(_xlpm.d="It","IT",_xlpm.d)) -> Operations | AI211: =_xlfn.LET(_xlpm.pid,tbl_FinancialData[[#This Row],[Product ID]],_xlpm.n,PROPER(TRIM(tbl_FinancialData[[#This Row],[Product Name]])),IF(_xlpm.pid="P020","Document Scanner",IF(_xlpm.pid="P015","Network Router",SUBSTITUTE(SUBSTITUTE(_xlpm.n,"Crm","CRM"),"Ups","UPS")))) -> Monitor | AJ211: =UPPER(TRIM(tbl_FinancialData[[#This Row],[Cost Center]])) -> CC-1002
A212: TXN-00211 | B212: 45920 | C212: September | D212: ="Q"&INT(MOD(MONTH(B212)-4,12)/3)+1 -> Q2 | E212: ="FY"& (YEAR(B212)+(MONTH(B212)>=4)) -> FY2026 | F212: West | G212: India | H212: Maharashtra | I212: Pune | J212: Branch B | K212: Sales | L212: CC-1004 | M212: P007 | N212: Tablet | O212: Electronics | P212: Mobile | Q212: 34917.73 | R212: 39264.36 | S212: 23280.56 | T212: 3871.26 | U212: 1299.01 | V212: 1643.61 | W212: 1203.38 | X212: 31297.81 | Y212: 11637.17 | Z212: =Q212-X212 -> 3619.92 | AA212: =Z212/Q212 -> 0.10366997 | AB212: -4346.63 | AC212: 1047.53 | AD212: 4064.42 | AE212: 37934.62 | AF212: =IF(tbl_FinancialData[[#This Row],[City]]="","Unknown",PROPER(TRIM(tbl_FinancialData[[#This Row],[City]]))) -> Pune | AG212: =_xlfn.LET(_xlpm.city,LOWER(TRIM(tbl_FinancialData[[#This Row],[City]])),_xlpm.st,PROPER(TRIM(tbl_FinancialData[[#This Row],[State]])),IF(_xlpm.city="pune","Maharashtra",IF(_xlpm.city="jamshedpur","Jharkhand",IF(_xlpm.city="bhilai","Chhattisgarh",IF(_xlpm.city="mumbai","Maharashtra",_xlpm.st))))) -> Maharashtra | AH212: =_xlfn.LET(_xlpm.d,PROPER(TRIM(tbl_FinancialData[[#This Row],[Department]])),IF(_xlpm.d="It","IT",_xlpm.d)) -> Sales | AI212: =_xlfn.LET(_xlpm.pid,tbl_FinancialData[[#This Row],[Product ID]],_xlpm.n,PROPER(TRIM(tbl_FinancialData[[#This Row],[Product Name]])),IF(_xlpm.pid="P020","Document Scanner",IF(_xlpm.pid="P015","Network Router",SUBSTITUTE(SUBSTITUTE(_xlpm.n,"Crm","CRM"),"Ups","UPS")))) -> Tablet | AJ212: =UPPER(TRIM(tbl_FinancialData[[#This Row],[Cost Center]])) -> CC-1004
A213: TXN-00212 | B213: 46004 | C213: December | D213: ="Q"&INT(MOD(MONTH(B213)-4,12)/3)+1 -> Q3 | E213: ="FY"& (YEAR(B213)+(MONTH(B213)>=4)) -> FY2026 | F213: East | G213: India | H213: Odisha | I213: Cuttack | J213: Branch A | K213: Marketing | L213: CC-1003 | M213: P015 | N213: Network Router | O213: Networking | P213: Network Equipment | Q213: 17482.77 | R213: 18882.34 | S213: 9747.11 | T213: 2129.99 | U213: 1446.31 | V213: 1154.27 | W213: 726.12 | X213: 15203.8 | Y213: 7735.66 | Z213: =Q213-X213 -> 2278.97 | AA213: =Z213/Q213 -> 0.1303552 | AB213: -1399.57 | AC213: 1748.28 | AD213: 2832.21 | AE213: 18566.7 | AF213: =IF(tbl_FinancialData[[#This Row],[City]]="","Unknown",PROPER(TRIM(tbl_FinancialData[[#This Row],[City]]))) -> Cuttack | AG213: =_xlfn.LET(_xlpm.city,LOWER(TRIM(tbl_FinancialData[[#This Row],[City]])),_xlpm.st,PROPER(TRIM(tbl_FinancialData[[#This Row],[State]])),IF(_xlpm.city="pune","Maharashtra",IF(_xlpm.city="jamshedpur","Jharkhand",IF(_xlpm.city="bhilai","Chhattisgarh",IF(_xlpm.city="mumbai","Maharashtra",_xlpm.st))))) -> Odisha | AH213: =_xlfn.LET(_xlpm.d,PROPER(TRIM(tbl_FinancialData[[#This Row],[Department]])),IF(_xlpm.d="It","IT",_xlpm.d)) -> Marketing | AI213: =_xlfn.LET(_xlpm.pid,tbl_FinancialData[[#This Row],[Product ID]],_xlpm.n,PROPER(TRIM(tbl_FinancialData[[#This Row],[Product Name]])),IF(_xlpm.pid="P020","Document Scanner",IF(_xlpm.pid="P015","Network Router",SUBSTITUTE(SUBSTITUTE(_xlpm.n,"Crm","CRM"),"Ups","UPS")))) -> Network Router | AJ213: =UPPER(TRIM(tbl_FinancialData[[#This Row],[Cost Center]])) -> CC-1003
A214: TXN-00213 | B214: 46005 | C214: December | D214: ="Q"&INT(MOD(MONTH(B214)-4,12)/3)+1 -> Q3 | E214: ="FY"& (YEAR(B214)+(MONTH(B214)>=4)) -> FY2026 | F214: West | G214: India | H214: Maharashtra | I214: Pune | J214: Branch A | K214: Sales | L214: CC-1003 | M214: P020 | N214: Document Scanner | O214: Electronics | P214: Office Equipment | Q214: 79192.1 | R214: 88727.18 | S214: 50827.24 | T214: 3995.83 | U214: 4377.63 | V214: 6786.21 | W214: 1634.61 | X214: 67621.53 | Y214: 28364.86 | Z214: =Q214-X214 -> 11570.57 | AA214: =Z214/Q214 -> 0.14610763 | AB214: -9535.08 | AC214: 1583.84 | AD214: 13969.49 | AE214: 91577.75 | AF214: =IF(tbl_FinancialData[[#This Row],[City]]="","Unknown",PROPER(TRIM(tbl_FinancialData[[#This Row],[City]]))) -> Pune | AG214: =_xlfn.LET(_xlpm.city,LOWER(TRIM(tbl_FinancialData[[#This Row],[City]])),_xlpm.st,PROPER(TRIM(tbl_FinancialData[[#This Row],[State]])),IF(_xlpm.city="pune","Maharashtra",IF(_xlpm.city="jamshedpur","Jharkhand",IF(_xlpm.city="bhilai","Chhattisgarh",IF(_xlpm.city="mumbai","Maharashtra",_xlpm.st))))) -> Maharashtra | AH214: =_xlfn.LET(_xlpm.d,PROPER(TRIM(tbl_FinancialData[[#This Row],[Department]])),IF(_xlpm.d="It","IT",_xlpm.d)) -> Sales | AI214: =_xlfn.LET(_xlpm.pid,tbl_FinancialData[[#This Row],[Product ID]],_xlpm.n,PROPER(TRIM(tbl_FinancialData[[#This Row],[Product Name]])),IF(_xlpm.pid="P020","Document Scanner",IF(_xlpm.pid="P015","Network Router",SUBSTITUTE(SUBSTITUTE(_xlpm.n,"Crm","CRM"),"Ups","UPS")))) -> Document Scanner | AJ214: =UPPER(TRIM(tbl_FinancialData[[#This Row],[Cost Center]])) -> CC-1003
A215: TXN-00214 | B215: 45934 | C215: October | D215: ="Q"&INT(MOD(MONTH(B215)-4,12)/3)+1 -> Q3 | E215: ="FY"& (YEAR(B215)+(MONTH(B215)>=4)) -> FY2026 | F215: West | G215: India | H215: Gujarat | I215: Vadodara | J215: Branch B | K215: Sales | L215: CC-1005 | M215: P003 | N215: Printer | O215: Electronics | P215: Office Equipment | Q215: 14247.77 | R215: 16455.9 | S215: 9253.61 | T215: 1064.54 | U215: 479.04 | V215: 1153.08 | W215: 145.14 | X215: 12095.42 | Y215: 4994.16 | Z215: =Q215-X215 -> 2152.35 | AA215: =Z215/Q215 -> 0.15106575 | AB215: -2208.13 | AC215: 1424.78 | AD215: 1538.76 | AE215: 14361.75 | AF215: =IF(tbl_FinancialData[[#This Row],[City]]="","Unknown",PROPER(TRIM(tbl_FinancialData[[#This Row],[City]]))) -> Vadodara | AG215: =_xlfn.LET(_xlpm.city,LOWER(TRIM(tbl_FinancialData[[#This Row],[City]])),_xlpm.st,PROPER(TRIM(tbl_FinancialData[[#This Row],[State]])),IF(_xlpm.city="pune","Maharashtra",IF(_xlpm.city="jamshedpur","Jharkhand",IF(_xlpm.city="bhilai","Chhattisgarh",IF(_xlpm.city="mumbai","Maharashtra",_xlpm.st))))) -> Gujarat | AH215: =_xlfn.LET(_xlpm.d,PROPER(TRIM(tbl_FinancialData[[#This Row],[Department]])),IF(_xlpm.d="It","IT",_xlpm.d)) -> Sales | AI215: =_xlfn.LET(_xlpm.pid,tbl_FinancialData[[#This Row],[Product ID]],_xlpm.n,PROPER(TRIM(tbl_FinancialData[[#This Row],[Product Name]])),IF(_xlpm.pid="P020","Document Scanner",IF(_xlpm.pid="P015","Network Router",SUBSTITUTE(SUBSTITUTE(_xlpm.n,"Crm","CRM"),"Ups","UPS")))) -> Printer | AJ215: =UPPER(TRIM(tbl_FinancialData[[#This Row],[Cost Center]])) -> CC-1005
A216: TXN-00215 | B216: 45872 | C216: August | D216: ="Q"&INT(MOD(MONTH(B216)-4,12)/3)+1 -> Q2 | E216: ="FY"& (YEAR(B216)+(MONTH(B216)>=4)) -> FY2026 | F216: West | G216: India | H216: Maharashtra | I216: Mumbai | J216: Branch A | K216: Marketing | L216: CC-1003 | M216: P002 | N216: Monitor | O216: Electronics | P216: Computing | Q216: 50404.03 | R216: 47816.42 | S216: 31414.03 | T216: 6262.93 | U216: 4304.21 | V216: 3394.83 | W216: 1434.94 | X216: 46810.94 | Y216: 18990 | Z216: =Q216-X216 -> 3593.09 | AA216: =Z216/Q216 -> 0.071285768 | AB216: 2587.61 | AC216: 1008.08 | AD216: 8891.27 | AE216: 58287.23 | AF216: =IF(tbl_FinancialData[[#This Row],[City]]="","Unknown",PROPER(TRIM(tbl_FinancialData[[#This Row],[City]]))) -> Mumbai | AG216: =_xlfn.LET(_xlpm.city,LOWER(TRIM(tbl_FinancialData[[#This Row],[City]])),_xlpm.st,PROPER(TRIM(tbl_FinancialData[[#This Row],[State]])),IF(_xlpm.city="pune","Maharashtra",IF(_xlpm.city="jamshedpur","Jharkhand",IF(_xlpm.city="bhilai","Chhattisgarh",IF(_xlpm.city="mumbai","Maharashtra",_xlpm.st))))) -> Maharashtra | AH216: =_xlfn.LET(_xlpm.d,PROPER(TRIM(tbl_FinancialData[[#This Row],[Department]])),IF(_xlpm.d="It","IT",_xlpm.d)) -> Marketing | AI216: =_xlfn.LET(_xlpm.pid,tbl_FinancialData[[#This Row],[Product ID]],_xlpm.n,PROPER(TRIM(tbl_FinancialData[[#This Row],[Product Name]])),IF(_xlpm.pid="P020","Document Scanner",IF(_xlpm.pid="P015","Network Router",SUBSTITUTE(SUBSTITUTE(_xlpm.n,"Crm","CRM"),"Ups","UPS")))) -> Monitor | AJ216: =UPPER(TRIM(tbl_FinancialData[[#This Row],[Cost Center]])) -> CC-1003
A217: TXN-00216 | B217: 46015 | C217: December | D217: ="Q"&INT(MOD(MONTH(B217)-4,12)/3)+1 -> Q3 | E217: ="FY"& (YEAR(B217)+(MONTH(B217)>=4)) -> FY2026 | F217: East | G217: India | H217: Odisha | I217: Bhubaneswar | J217: Branch B | K217: Marketing | L217: CC-1001 | M217: P014 | N217: Data Storage | O217: Software | P217: Cloud Services | Q217: 6369.34 | R217: 6894.41 | S217: 4092.99 | T217: 508.59 | U217: 549.1 | V217: 340.05 | W217: 175.24 | X217: 5665.97 | Y217: 2276.36 | Z217: =Q217-X217 -> 703.37 | AA217: =Z217/Q217 -> 0.11043059 | AB217: -525.06 | AC217: 318.47 | AD217: 1089.16 | AE217: 7140.04 | AF217: =IF(tbl_FinancialData[[#This Row],[City]]="","Unknown",PROPER(TRIM(tbl_FinancialData[[#This Row],[City]]))) -> Bhubaneswar | AG217: =_xlfn.LET(_xlpm.city,LOWER(TRIM(tbl_FinancialData[[#This Row],[City]])),_xlpm.st,PROPER(TRIM(tbl_FinancialData[[#This Row],[State]])),IF(_xlpm.city="pune","Maharashtra",IF(_xlpm.city="jamshedpur","Jharkhand",IF(_xlpm.city="bhilai","Chhattisgarh",IF(_xlpm.city="mumbai","Maharashtra",_xlpm.st))))) -> Odisha | AH217: =_xlfn.LET(_xlpm.d,PROPER(TRIM(tbl_FinancialData[[#This Row],[Department]])),IF(_xlpm.d="It","IT",_xlpm.d)) -> Marketing | AI217: =_xlfn.LET(_xlpm.pid,tbl_FinancialData[[#This Row],[Product ID]],_xlpm.n,PROPER(TRIM(tbl_FinancialData[[#This Row],[Product Name]])),IF(_xlpm.pid="P020","Document Scanner",IF(_xlpm.pid="P015","Network Router",SUBSTITUTE(SUBSTITUTE(_xlpm.n,"Crm","CRM"),"Ups","UPS")))) -> Data Storage | AJ217: =UPPER(TRIM(tbl_FinancialData[[#This Row],[Cost Center]])) -> CC-1001
A218: TXN-00217 | B218: 45929 | C218: September | D218: ="Q"&INT(MOD(MONTH(B218)-4,12)/3)+1 -> Q2 | E218: ="FY"& (YEAR(B218)+(MONTH(B218)>=4)) -> FY2026 | F218: South | G218: India | H218: Telangana | I218: Hyderabad | J218: Branch D | K218: Marketing | L218: CC-1001 | M218: P015 | N218: Network Router | O218: Networking | P218: Network Equipment | Q218: 9860.57 | R218: 10392.23 | S218: 5804.9 | T218: 1241.44 | U218: 285.36 | V218: 935.09 | W218: 107.22 | X218: 8374.02 | Y218: 4055.67 | Z218: =Q218-X218 -> 1486.55 | AA218: =Z218/Q218 -> 0.150757 | AB218: -531.66 | AC218: 0 | AD218: 1183.27 | AE218: 11043.84 | AF218: =IF(tbl_FinancialData[[#This Row],[City]]="","Unknown",PROPER(TRIM(tbl_FinancialData[[#This Row],[City]]))) -> Hyderabad | AG218: =_xlfn.LET(_xlpm.city,LOWER(TRIM(tbl_FinancialData[[#This Row],[City]])),_xlpm.st,PROPER(TRIM(tbl_FinancialData[[#This Row],[State]])),IF(_xlpm.city="pune","Maharashtra",IF(_xlpm.city="jamshedpur","Jharkhand",IF(_xlpm.city="bhilai","Chhattisgarh",IF(_xlpm.city="mumbai","Maharashtra",_xlpm.st))))) -> Telangana | AH218: =_xlfn.LET(_xlpm.d,PROPER(TRIM(tbl_FinancialData[[#This Row],[Department]])),IF(_xlpm.d="It","IT",_xlpm.d)) -> Marketing | AI218: =_xlfn.LET(_xlpm.pid,tbl_FinancialData[[#This Row],[Product ID]],_xlpm.n,PROPER(TRIM(tbl_FinancialData[[#This Row],[Product Name]])),IF(_xlpm.pid="P020","Document Scanner",IF(_xlpm.pid="P015","Network Router",SUBSTITUTE(SUBSTITUTE(_xlpm.n,"Crm","CRM"),"Ups","UPS")))) -> Network Router | AJ218: =UPPER(TRIM(tbl_FinancialData[[#This Row],[Cost Center]])) -> CC-1001
A219: TXN-00218 | B219: 46043 | C219: January | D219: ="Q"&INT(MOD(MONTH(B219)-4,12)/3)+1 -> Q4 | E219: ="FY"& (YEAR(B219)+(MONTH(B219)>=4)) -> FY2026 | F219: West | G219: India | H219: Gujarat | I219: Surat | J219: Branch C | K219: Operations | L219: CC-1002 | M219: P013 | N219: CRM Software | O219: Software | P219: Business Software | Q219: 9333.46 | R219: 8989.09 | S219: 6543.81 | T219: 902.13 | U219: 593 | V219: 638.35 | W219: 110.32 | X219: 8787.61 | Y219: 2789.64 | Z219: =Q219-X219 -> 545.85 | AA219: =Z219/Q219 -> 0.058483135 | AB219: 344.37 | AC219: 0 | AD219: 1120.01 | AE219: 10453.47 | AF219: =IF(tbl_FinancialData[[#This Row],[City]]="","Unknown",PROPER(TRIM(tbl_FinancialData[[#This Row],[City]]))) -> Surat | AG219: =_xlfn.LET(_xlpm.city,LOWER(TRIM(tbl_FinancialData[[#This Row],[City]])),_xlpm.st,PROPER(TRIM(tbl_FinancialData[[#This Row],[State]])),IF(_xlpm.city="pune","Maharashtra",IF(_xlpm.city="jamshedpur","Jharkhand",IF(_xlpm.city="bhilai","Chhattisgarh",IF(_xlpm.city="mumbai","Maharashtra",_xlpm.st))))) -> Gujarat | AH219: =_xlfn.LET(_xlpm.d,PROPER(TRIM(tbl_FinancialData[[#This Row],[Department]])),IF(_xlpm.d="It","IT",_xlpm.d)) -> Operations | AI219: =_xlfn.LET(_xlpm.pid,tbl_FinancialData[[#This Row],[Product ID]],_xlpm.n,PROPER(TRIM(tbl_FinancialData[[#This Row],[Product Name]])),IF(_xlpm.pid="P020","Document Scanner",IF(_xlpm.pid="P015","Network Router",SUBSTITUTE(SUBSTITUTE(_xlpm.n,"Crm","CRM"),"Ups","UPS")))) -> CRM Software | AJ219: =UPPER(TRIM(tbl_FinancialData[[#This Row],[Cost Center]])) -> CC-1002
... A1001: TXN-01000 | B1001: 46000 | C1001: December | D1001: ="Q"&INT(MOD(MONTH(B1001)-4,12)/3)+1 -> Q3 | E1001: ="FY"& (YEAR(B1001)+(MONTH(B1001)>=4)) -> FY2026 | F1001: West | G1001: India | H1001: Maharashtra | I1001: Nagpur | J1001: Branch A | K1001: Finance | L1001: CC-1003 | M1001: P016 | N1001: Network Switch | O1001: Networking | P1001: Network Equipment | Q1001: 34733.42 | R1001: 30619.73 | S1001: 24454.69 | T1001: 3158 | U1001: 2450.36 | V1001: 3766.84 | W1001: 915.18 | X1001: 34745.07 | Y1001: 10278.73 | Z1001: =Q1001-X1001 -> -11.65 | AA1001: =Z1001/Q1001 -> -0.00033541183 | AB1001: 4113.7 | AC1001: 2778.67 | AD1001: 1597.74 | AE1001: 33552.49 | AF1001: =IF(tbl_FinancialData[[#This Row],[City]]="","Unknown",PROPER(TRIM(tbl_FinancialData[[#This Row],[City]]))) -> Nagpur | AG1001: =_xlfn.LET(_xlpm.city,LOWER(TRIM(tbl_FinancialData[[#This Row],[City]])),_xlpm.st,PROPER(TRIM(tbl_FinancialData[[#This Row],[State]])),IF(_xlpm.city="pune","Maharashtra",IF(_xlpm.city="jamshedpur","Jharkhand",IF(_xlpm.city="bhilai","Chhattisgarh",IF(_xlpm.city="mumbai","Maharashtra",_xlpm.st))))) -> Maharashtra | AH1001: =_xlfn.LET(_xlpm.d,PROPER(TRIM(tbl_FinancialData[[#This Row],[Department]])),IF(_xlpm.d="It","IT",_xlpm.d)) -> Finance | AI1001: =_xlfn.LET(_xlpm.pid,tbl_FinancialData[[#This Row],[Product ID]],_xlpm.n,PROPER(TRIM(tbl_FinancialData[[#This Row],[Product Name]])),IF(_xlpm.pid="P020","Document Scanner",IF(_xlpm.pid="P015","Network Router",SUBSTITUTE(SUBSTITUTE(_xlpm.n,"Crm","CRM"),"Ups","UPS")))) -> Network Switch | AJ1001: =UPPER(TRIM(tbl_FinancialData[[#This Row],[Cost Center]])) -> CC-1003

Sheet Calculation
B1: FINANCIAL PERFORMANCE CALCULATION
B3: CORE FINANCIAL KPIs | E3: PROFITABILITY KPIs | H3: SALES & ORDER KPIs | K3: BUDGET PERFORMANCE | N3: FINANCIAL CONTROL CHECK
B5: Metric | C5: Value | E5: Metric | F5: Value | H5: Metric | I5: Value | K5: Metric | L5: Value | N5: Metric | O5: Value
B6: Total Revenue | C6: =SUM(tbl_FinancialData[Revenue]) -> 28075370 | E6: Gross Profit Margin % | F6: =IF(C16=0,0,C14/C16) -> 0.36874696 | H6: Total Transactions | I6: =COUNTA(tbl_FinancialData[Transaction ID]) -> 1000 | K6: Total Budget Revenue | L6: =C7 -> 29125875 | N6: Revenue Check | O6: =IF(C6=SUM(tbl_FinancialData[Revenue]),"PASS","CHECK") -> PASS
B7: Total Budget Revenue | C7: =SUM(tbl_FinancialData[Budget Revenue]) -> 29125875 | E7: Net Profit Margin % | F7: =IF(C16=0,0,C15/C16) -> 0.13343412 | H7: Total Tax | I7: =SUM(tbl_FinancialData[Tax]) -> 3388579.6 | K7: Actual Revenue | L7: =C6 -> 28075370 | N7: Profit Check | O7: =IF(C15=SUM(tbl_FinancialData[Net Profit]),"PASS","CHECK") -> PASS
B8: Total COGS | C8: =SUM(tbl_FinancialData[COGS]) -> 16885275 | E8: COGS % of Revenue | F8: =IF(C6=0,0,C8/C6) -> 0.6014266 | H8: Average Revenue / Transaction | I8: =IF(I6=0,0,C6/I6) -> 28075.37 | K8: Budget Variance | L8: =L7-L6 -> -1050504.6 | N8: Expense Check | O8: =IF(C13=SUM(tbl_FinancialData[Total Expense]),"PASS","CHECK") -> PASS
B9: Total Operating Expense | C9: =SUM(tbl_FinancialData[Operating Expense]) -> 2553433.5 | E9: Operating Expense % | F9: =IF(C6=0,0,C9/C6) -> 0.090949238 | H9: Average Net Revenue | I9: =IF(I6=0,0,C16/I6) -> 30346.272 | K9: Budget Achievement % | L9: =IF(L6=0,0,L7/L6) -> 0.96393226 | N9: Budget Variance Check | O9: =IF(L8=L7-L6,"PASS","CHECK") -> PASS
B10: Total Marketing Expense | C10: =SUM(tbl_FinancialData[Marketing Expense]) -> 1601652.6 | E10: Marketing Expense % | F10: =IF(C6=0,0,C10/C6) -> 0.057048316 | H10: Average Profit / Transaction | I10: =IF(I6=0,0,C15/I6) -> 4049.2281 | K10: Above Budget Transactions | L10: {=SUMPRODUCT(--(tbl_FinancialData[Revenue]>tbl_FinancialData[Budget Revenue]))} -> 393 | N10: Profit Margin Check | O10: =IF(ABS(F7-(C15/C16))<0.000001,"PASS","CHECK") -> PASS
B11: Total Salary Expense | C11: =SUM(tbl_FinancialData[Salary Expense]) -> 2240126.7 | E11: Salary Expense % | F11: =IF(C6=0,0,C11/C6) -> 0.079789748 | H11: Maximum Revenue | I11: =MAX(tbl_FinancialData[Revenue]) -> 82566.39 | K11: Below Budget Transactions | L11: {=SUMPRODUCT(--(tbl_FinancialData[Revenue]<tbl_FinancialData[Budget Revenue]))} -> 607 | N11: Negative Profit Check | O11: =COUNTIF(tbl_FinancialData[Net Profit],"<0") -> 26
B12: Total Misc Expense | C12: =SUM(tbl_FinancialData[Misc Expense]) -> 745654.55 | E12: Expense Ratio % | F12: =IF(C6=0,0,C13/C6) -> 0.85577294 | H12: Minimum Revenue | I12: =MIN(tbl_FinancialData[Revenue]) -> 997.19 | N12: Missing Revenue | O12: =COUNTBLANK(tbl_FinancialData[Revenue]) -> 0
B13: Total Expense | C13: =SUM(tbl_FinancialData[Total Expense]) -> 24026142 | E13: Tax % of Revenue | F13: =IF(C6=0,0,SUM(tbl_FinancialData[Tax])/C6) -> 0.12069581 | H13: Average Discount Amount | I13: =AVERAGE(tbl_FinancialData[Discount]) -> 1117.6776 | N13: Overall Data Status | O13: =IF(COUNTIF(O6:O10,"CHECK")=0,"PASS","CHECK") -> PASS
B14: Gross Profit | C14: =SUM(tbl_FinancialData[Gross Profit]) -> 11190096
B15: Net Profit | C15: =SUM(tbl_FinancialData[Net Profit]) -> 4049228.1
B16: Net Revenue | C16: =SUM(tbl_FinancialData[Net Revenue]) -> 30346272
B19: MONTHLY PERFORMANCE | H19: PRODUCT PERFORMANCE
B21: Month | C21: Revenue | D21: Net Revenue | F21: Net Profit | H21: Product Name | I21: Revenue | K21: Net Revenue | L21: Net Profit | N21: Profit Margin %
B22: January | C22: =SUMIFS(tbl_FinancialData[Revenue],tbl_FinancialData[Month],B22) -> 2181355.6 | D22: =SUMIFS(tbl_FinancialData[Net Revenue],tbl_FinancialData[Month],B22) -> 2372895.5 | F22: =SUMIFS(tbl_FinancialData[Net Profit],tbl_FinancialData[Month],B22) -> 366183.01 | H22: {=_xlfn.UNIQUE(tbl_FinancialData[Clean Product Name])} -> Conference Camera | I22: =SUMIFS(tbl_FinancialData[Revenue],tbl_FinancialData[Clean Product Name],H22) -> 2339747.2 | K22: =SUMIFS(tbl_FinancialData[Net Revenue],tbl_FinancialData[Clean Product Name],H22) -> 2563627 | L22: =SUMIFS(tbl_FinancialData[Net Profit],tbl_FinancialData[Clean Product Name],H22) -> 352156.89 | N22: =IF(K22=0,0,L22/K22) -> 0.13736666
B23: February | C23: =SUMIFS(tbl_FinancialData[Revenue],tbl_FinancialData[Month],B23) -> 1911886.9 | D23: =SUMIFS(tbl_FinancialData[Net Revenue],tbl_FinancialData[Month],B23) -> 2058530.9 | F23: =SUMIFS(tbl_FinancialData[Net Profit],tbl_FinancialData[Month],B23) -> 264165.76 | H23: Mouse | I23: =SUMIFS(tbl_FinancialData[Revenue],tbl_FinancialData[Clean Product Name],H23) -> 342884.68 | K23: =SUMIFS(tbl_FinancialData[Net Revenue],tbl_FinancialData[Clean Product Name],H23) -> 371332.23 | L23: =SUMIFS(tbl_FinancialData[Net Profit],tbl_FinancialData[Clean Product Name],H23) -> 51211.29 | N23: =IF(K23=0,0,L23/K23) -> 0.13791232
B24: March | C24: =SUMIFS(tbl_FinancialData[Revenue],tbl_FinancialData[Month],B24) -> 2601921.4 | D24: =SUMIFS(tbl_FinancialData[Net Revenue],tbl_FinancialData[Month],B24) -> 2807903.3 | F24: =SUMIFS(tbl_FinancialData[Net Profit],tbl_FinancialData[Month],B24) -> 380179.07 | H24: Keyboard | I24: =SUMIFS(tbl_FinancialData[Revenue],tbl_FinancialData[Clean Product Name],H24) -> 223374.13 | K24: =SUMIFS(tbl_FinancialData[Net Revenue],tbl_FinancialData[Clean Product Name],H24) -> 242203.65 | L24: =SUMIFS(tbl_FinancialData[Net Profit],tbl_FinancialData[Clean Product Name],H24) -> 33471.57 | N24: =IF(K24=0,0,L24/K24) -> 0.13819598
B25: April | C25: =SUMIFS(tbl_FinancialData[Revenue],tbl_FinancialData[Month],B25) -> 2623231 | D25: =SUMIFS(tbl_FinancialData[Net Revenue],tbl_FinancialData[Month],B25) -> 2840517.9 | F25: =SUMIFS(tbl_FinancialData[Net Profit],tbl_FinancialData[Month],B25) -> 339729.95 | H25: Monitor | I25: =SUMIFS(tbl_FinancialData[Revenue],tbl_FinancialData[Clean Product Name],H25) -> 2193240.1 | K25: =SUMIFS(tbl_FinancialData[Net Revenue],tbl_FinancialData[Clean Product Name],H25) -> 2321909.5 | L25: =SUMIFS(tbl_FinancialData[Net Profit],tbl_FinancialData[Clean Product Name],H25) -> 300414.71 | N25: =IF(K25=0,0,L25/K25) -> 0.12938261
B26: May | C26: =SUMIFS(tbl_FinancialData[Revenue],tbl_FinancialData[Month],B26) -> 2589723.3 | D26: =SUMIFS(tbl_FinancialData[Net Revenue],tbl_FinancialData[Month],B26) -> 2814374 | F26: =SUMIFS(tbl_FinancialData[Net Profit],tbl_FinancialData[Month],B26) -> 390479.72 | H26: Business Laptop | I26: =SUMIFS(tbl_FinancialData[Revenue],tbl_FinancialData[Clean Product Name],H26) -> 1944377.2 | K26: =SUMIFS(tbl_FinancialData[Net Revenue],tbl_FinancialData[Clean Product Name],H26) -> 2120819.8 | L26: =SUMIFS(tbl_FinancialData[Net Profit],tbl_FinancialData[Clean Product Name],H26) -> 289724.32 | N26: =IF(K26=0,0,L26/K26) -> 0.13660959
B27: June | C27: =SUMIFS(tbl_FinancialData[Revenue],tbl_FinancialData[Month],B27) -> 1864173.1 | D27: =SUMIFS(tbl_FinancialData[Net Revenue],tbl_FinancialData[Month],B27) -> 1998125.5 | F27: =SUMIFS(tbl_FinancialData[Net Profit],tbl_FinancialData[Month],B27) -> 256654.28 | H27: Printer | I27: =SUMIFS(tbl_FinancialData[Revenue],tbl_FinancialData[Clean Product Name],H27) -> 2045797 | K27: =SUMIFS(tbl_FinancialData[Net Revenue],tbl_FinancialData[Clean Product Name],H27) -> 2220027.3 | L27: =SUMIFS(tbl_FinancialData[Net Profit],tbl_FinancialData[Clean Product Name],H27) -> 294715.27 | N27: =IF(K27=0,0,L27/K27) -> 0.13275299
B28: July | C28: =SUMIFS(tbl_FinancialData[Revenue],tbl_FinancialData[Month],B28) -> 2377772.4 | D28: =SUMIFS(tbl_FinancialData[Net Revenue],tbl_FinancialData[Month],B28) -> 2569787.4 | F28: =SUMIFS(tbl_FinancialData[Net Profit],tbl_FinancialData[Month],B28) -> 358652.4 | H28: Document Scanner | I28: =SUMIFS(tbl_FinancialData[Revenue],tbl_FinancialData[Clean Product Name],H28) -> 2452090 | K28: =SUMIFS(tbl_FinancialData[Net Revenue],tbl_FinancialData[Clean Product Name],H28) -> 2640552.1 | L28: =SUMIFS(tbl_FinancialData[Net Profit],tbl_FinancialData[Clean Product Name],H28) -> 402031.39 | N28: =IF(K28=0,0,L28/K28) -> 0.15225278
B29: August | C29: =SUMIFS(tbl_FinancialData[Revenue],tbl_FinancialData[Month],B29) -> 2205648.3 | D29: =SUMIFS(tbl_FinancialData[Net Revenue],tbl_FinancialData[Month],B29) -> 2430495.1 | F29: =SUMIFS(tbl_FinancialData[Net Profit],tbl_FinancialData[Month],B29) -> 304569.7 | H29: Accounting Software | I29: =SUMIFS(tbl_FinancialData[Revenue],tbl_FinancialData[Clean Product Name],H29) -> 844749.68 | K29: =SUMIFS(tbl_FinancialData[Net Revenue],tbl_FinancialData[Clean Product Name],H29) -> 926660.45 | L29: =SUMIFS(tbl_FinancialData[Net Profit],tbl_FinancialData[Clean Product Name],H29) -> 115635.16 | N29: =IF(K29=0,0,L29/K29) -> 0.12478698
B30: September | C30: =SUMIFS(tbl_FinancialData[Revenue],tbl_FinancialData[Month],B30) -> 2117877.9 | D30: =SUMIFS(tbl_FinancialData[Net Revenue],tbl_FinancialData[Month],B30) -> 2281461.2 | F30: =SUMIFS(tbl_FinancialData[Net Profit],tbl_FinancialData[Month],B30) -> 280013.7 | H30: Office Desk | I30: =SUMIFS(tbl_FinancialData[Revenue],tbl_FinancialData[Clean Product Name],H30) -> 971560.77 | K30: =SUMIFS(tbl_FinancialData[Net Revenue],tbl_FinancialData[Clean Product Name],H30) -> 1048893.8 | L30: =SUMIFS(tbl_FinancialData[Net Profit],tbl_FinancialData[Clean Product Name],H30) -> 149953.57 | N30: =IF(K30=0,0,L30/K30) -> 0.14296354
B31: October | C31: =SUMIFS(tbl_FinancialData[Revenue],tbl_FinancialData[Month],B31) -> 2173483.1 | D31: =SUMIFS(tbl_FinancialData[Net Revenue],tbl_FinancialData[Month],B31) -> 2327518.2 | F31: =SUMIFS(tbl_FinancialData[Net Profit],tbl_FinancialData[Month],B31) -> 316399.42 | H31: Projector | I31: =SUMIFS(tbl_FinancialData[Revenue],tbl_FinancialData[Clean Product Name],H31) -> 2203534.8 | K31: =SUMIFS(tbl_FinancialData[Net Revenue],tbl_FinancialData[Clean Product Name],H31) -> 2395220.6 | L31: =SUMIFS(tbl_FinancialData[Net Profit],tbl_FinancialData[Clean Product Name],H31) -> 332435.91 | N31: =IF(K31=0,0,L31/K31) -> 0.13879136
B32: November | C32: =SUMIFS(tbl_FinancialData[Revenue],tbl_FinancialData[Month],B32) -> 2665320.7 | D32: =SUMIFS(tbl_FinancialData[Net Revenue],tbl_FinancialData[Month],B32) -> 2863485.4 | F32: =SUMIFS(tbl_FinancialData[Net Profit],tbl_FinancialData[Month],B32) -> 407916.85 | H32: UPS System | I32: =SUMIFS(tbl_FinancialData[Revenue],tbl_FinancialData[Clean Product Name],H32) -> 2426113.9 | K32: =SUMIFS(tbl_FinancialData[Net Revenue],tbl_FinancialData[Clean Product Name],H32) -> 2608394.8 | L32: =SUMIFS(tbl_FinancialData[Net Profit],tbl_FinancialData[Clean Product Name],H32) -> 329561.61 | N32: =IF(K32=0,0,L32/K32) -> 0.12634652
B33: December | C33: =SUMIFS(tbl_FinancialData[Revenue],tbl_FinancialData[Month],B33) -> 2762976.5 | D33: =SUMIFS(tbl_FinancialData[Net Revenue],tbl_FinancialData[Month],B33) -> 2981178.1 | F33: =SUMIFS(tbl_FinancialData[Net Profit],tbl_FinancialData[Month],B33) -> 384284.26 | H33: Headset | I33: =SUMIFS(tbl_FinancialData[Revenue],tbl_FinancialData[Clean Product Name],H33) -> 287113.26 | K33: =SUMIFS(tbl_FinancialData[Net Revenue],tbl_FinancialData[Clean Product Name],H33) -> 307144 | L33: =SUMIFS(tbl_FinancialData[Net Profit],tbl_FinancialData[Clean Product Name],H33) -> 41741.94 | N33: =IF(K33=0,0,L33/K33) -> 0.13590349
B34: Total | C34: =SUM(C22:C33) -> 28075370 | D34: =SUM(D22:D33) -> 30346272 | F34: =SUM(F22:F33) -> 4049228.1 | H34: Tablet | I34: =SUMIFS(tbl_FinancialData[Revenue],tbl_FinancialData[Clean Product Name],H34) -> 1831477.7 | K34: =SUMIFS(tbl_FinancialData[Net Revenue],tbl_FinancialData[Clean Product Name],H34) -> 1983164 | L34: =SUMIFS(tbl_FinancialData[Net Profit],tbl_FinancialData[Clean Product Name],H34) -> 213179.73 | N34: =IF(K34=0,0,L34/K34) -> 0.10749476
H35: Network Switch | I35: =SUMIFS(tbl_FinancialData[Revenue],tbl_FinancialData[Clean Product Name],H35) -> 1273809.8 | K35: =SUMIFS(tbl_FinancialData[Net Revenue],tbl_FinancialData[Clean Product Name],H35) -> 1366829.2 | L35: =SUMIFS(tbl_FinancialData[Net Profit],tbl_FinancialData[Clean Product Name],H35) -> 173377.79 | N35: =IF(K35=0,0,L35/K35) -> 0.12684671
B36: REGIONAL PERFORMANCE | H36: Network Router | I36: =SUMIFS(tbl_FinancialData[Revenue],tbl_FinancialData[Clean Product Name],H36) -> 1197583.1 | K36: =SUMIFS(tbl_FinancialData[Net Revenue],tbl_FinancialData[Clean Product Name],H36) -> 1285482 | L36: =SUMIFS(tbl_FinancialData[Net Profit],tbl_FinancialData[Clean Product Name],H36) -> 170136.85 | N36: =IF(K36=0,0,L36/K36) -> 0.13235258
H37: CRM Software | I37: =SUMIFS(tbl_FinancialData[Revenue],tbl_FinancialData[Clean Product Name],H37) -> 985676.13 | K37: =SUMIFS(tbl_FinancialData[Net Revenue],tbl_FinancialData[Clean Product Name],H37) -> 1045782.7 | L37: =SUMIFS(tbl_FinancialData[Net Profit],tbl_FinancialData[Clean Product Name],H37) -> 135857.69 | N37: =IF(K37=0,0,L37/K37) -> 0.12991005
B38: Region | C38: Net Revenue | D38: Net Profit | F38: Profit Margin % | H38: Smartphone | I38: =SUMIFS(tbl_FinancialData[Revenue],tbl_FinancialData[Clean Product Name],H38) -> 2111913.1 | K38: =SUMIFS(tbl_FinancialData[Net Revenue],tbl_FinancialData[Clean Product Name],H38) -> 2301634.8 | L38: =SUMIFS(tbl_FinancialData[Net Profit],tbl_FinancialData[Clean Product Name],H38) -> 305953.15 | N38: =IF(K38=0,0,L38/K38) -> 0.13292863
B39: {=_xlfn.UNIQUE(tbl_FinancialData[Region])} -> West | C39: =SUMIFS(tbl_FinancialData[Net Revenue],tbl_FinancialData[Region],B39) -> 8752932.8 | D39: =SUMIFS(tbl_FinancialData[Net Profit],tbl_FinancialData[Region],B39) -> 1153460.7 | F39: =IF(C39=0,0,D39/C39) -> 0.13177991 | H39: Office Chair | I39: =SUMIFS(tbl_FinancialData[Revenue],tbl_FinancialData[Clean Product Name],H39) -> 1054216.9 | K39: =SUMIFS(tbl_FinancialData[Net Revenue],tbl_FinancialData[Clean Product Name],H39) -> 1133910 | L39: =SUMIFS(tbl_FinancialData[Net Profit],tbl_FinancialData[Clean Product Name],H39) -> 156411.06 | N39: =IF(K39=0,0,L39/K39) -> 0.13793957
B40: South | C40: =SUMIFS(tbl_FinancialData[Net Revenue],tbl_FinancialData[Region],B40) -> 5662312.4 | D40: =SUMIFS(tbl_FinancialData[Net Profit],tbl_FinancialData[Region],B40) -> 766054.11 | F40: =IF(C40=0,0,D40/C40) -> 0.13528998 | H40: Cloud Software | I40: =SUMIFS(tbl_FinancialData[Revenue],tbl_FinancialData[Clean Product Name],H40) -> 590733.28 | K40: =SUMIFS(tbl_FinancialData[Net Revenue],tbl_FinancialData[Clean Product Name],H40) -> 638903.03 | L40: =SUMIFS(tbl_FinancialData[Net Profit],tbl_FinancialData[Clean Product Name],H40) -> 86677.21 | N40: =IF(K40=0,0,L40/K40) -> 0.13566567
B41: North | C41: =SUMIFS(tbl_FinancialData[Net Revenue],tbl_FinancialData[Region],B41) -> 6212876.2 | D41: =SUMIFS(tbl_FinancialData[Net Profit],tbl_FinancialData[Region],B41) -> 803367.8 | F41: =IF(C41=0,0,D41/C41) -> 0.12930691 | H41: Data Storage | I41: =SUMIFS(tbl_FinancialData[Revenue],tbl_FinancialData[Clean Product Name],H41) -> 755377.32 | K41: =SUMIFS(tbl_FinancialData[Net Revenue],tbl_FinancialData[Clean Product Name],H41) -> 823781.7 | L41: =SUMIFS(tbl_FinancialData[Net Profit],tbl_FinancialData[Clean Product Name],H41) -> 114581.01 | N41: =IF(K41=0,0,L41/K41) -> 0.13909147
B42: East | C42: =SUMIFS(tbl_FinancialData[Net Revenue],tbl_FinancialData[Region],B42) -> 5762219.9 | D42: =SUMIFS(tbl_FinancialData[Net Profit],tbl_FinancialData[Region],B42) -> 797440.02 | F42: =IF(C42=0,0,D42/C42) -> 0.13839111 | H42: Total | I42: =SUM(I22:I41) -> 28075370 | K42: =SUM(K22:K41) -> 30346272 | L42: =SUM(L22:L41) -> 4049228.1 | N42: =IF(K42=0,0,L42/K42) -> 0.13343412
B43: Central | C43: =SUMIFS(tbl_FinancialData[Net Revenue],tbl_FinancialData[Region],B43) -> 3955931.1 | D43: =SUMIFS(tbl_FinancialData[Net Profit],tbl_FinancialData[Region],B43) -> 528905.52 | F43: =IF(C43=0,0,D43/C43) -> 0.13369938
B46: MANAGEMENT INSIGHTS
B51: =INDEX(B39:B43,MATCH(MAX(C39:C43),C39:C43,0)) -> West | C51: =INDEX(B39:B43,MATCH(MIN(C39:C43),C39:C43,0)) -> Central | E51: =INDEX(B22:B33,MATCH(MAX(F22:F33),F22:F33,0)) -> November | G51: =INDEX(B22:B33,MATCH(MIN(F22:F33),F22:F33,0)) -> June | I51: =INDEX(B39:B43,MATCH(MAX(D39:D43),D39:D43,0)) -> West | K51: =INDEX(H22:H41, MATCH(MAX(I22:I41), I22:I41, 0)) -> Document Scanner | L51: =L9 -> 0.96393226 | N51: =IF(C16=0,0,C15/C16) -> 0.13343412

Sheet Pivot_Analysis
A1: FINANCIAL PERFORMANCE DASHBOARD – PIVOT ANALYSIS
A3: REGIONAL PERFORMANCE | F3: Product Category Performance | K3: MONTHLY REVENUE PERFORMANCE
A5: Row Labels | B5: Sum of Revenue | C5: Sum of Budget Revenue | D5: Sum of Net Profit | F5: Row Labels | G5: Sum of Revenue | H5: Sum of Net Profit | I5: Sum of Category Profit Margin % | K5: Row Labels | L5: Sum of Revenue | M5: Sum of Budget Revenue
A6: Central | B6: 3662391.3 | C6: 3801955.5 | D6: 528905.52 | F6: Electronics | G6: 19548291 | H6: 2820173 | I6: 0.14426698 | K6: January | L6: 2181355.6 | M6: 2276512.1
A7: East | B7: 5352186.6 | C7: 5499615.9 | D7: 797440.02 | F7: Software | G7: 3176536.4 | H7: 452751.07 | I7: 0.14252979 | K7: February | L7: 1911886.9 | M7: 1968499.2
A8: North | B8: 5755442.3 | C8: 6052506.8 | D8: 803367.8 | F8: Networking | G8: 2471393 | H8: 343514.64 | I8: 0.13899637 | K8: March | L8: 2601921.4 | M8: 2683466.9
A9: South | B9: 5236399.6 | C9: 5380990.9 | D9: 766054.11 | F9: Furniture | G9: 2025777.6 | H9: 306364.63 | I9: 0.1512331 | K9: April | L9: 2623231 | M9: 2718448.3
A10: West | B10: 8068950.3 | C10: 8390805.7 | D10: 1153460.7 | F10: Accessories | G10: 853372.07 | H10: 126424.8 | I10: 0.14814734 | K10: May | L10: 2589723.3 | M10: 2707793.3
A11: Grand Total | B11: 28075370 | C11: 29125875 | D11: 4049228.1 | F11: Grand Total | G11: 28075370 | H11: 4049228.1 | I11: 0.14422706 | K11: June | L11: 1864173.1 | M11: 1904464.2
K12: July | L12: 2377772.4 | M12: 2489475.1
A13: DEPARTMENT PERFORMANCE | F13: BUDGET VS ACTUAL PERFORMANCE | K13: August | L13: 2205648.3 | M13: 2253578.6
K14: September | L14: 2117877.9 | M14: 2200483
A15: Row Labels | B15: Sum of Revenue | C15: Sum of Total Expense | D15: Sum of Net Profit | F15: Row Labels | G15: Sum of Revenue | H15: Sum of Budget Revenue | I15: Sum of Budget Variance | K15: October | L15: 2173483.1 | M15: 2284313.1
A16: Sales | B16: 11324026 | C16: 9704157.5 | D16: 1619868.4 | F16: Central | G16: 3662391.3 | H16: 3801955.5 | I16: -139564.17 | K16: November | L16: 2665320.7 | M16: 2766859.1
A17: Operations | B17: 5525491.1 | C17: 4701121.6 | D17: 824369.5 | F17: East | G17: 5352186.6 | H17: 5499615.9 | I17: -147429.27 | K17: December | L17: 2762976.5 | M17: 2871981.8
A18: Marketing | B18: 4440019.1 | C18: 3787513.4 | D18: 652505.76 | F18: North | G18: 5755442.3 | H18: 6052506.8 | I18: -297064.46 | K18: Grand Total | L18: 28075370 | M18: 29125875
A19: Finance | B19: 3360643.6 | C19: 2877531 | D19: 483112.56 | F19: South | G19: 5236399.6 | H19: 5380990.9 | I19: -144591.28
A20: IT | B20: 3425190.3 | C20: 2955818.5 | D20: 469371.85 | F20: West | G20: 8068950.3 | H20: 8390805.7 | I20: -321855.46
A21: Grand Total | B21: 28075370 | C21: 24026142 | D21: 4049228.1 | F21: Grand Total | G21: 28075370 | H21: 29125875 | I21: -1050504.6
A24: QUARTERLY PERFORMANCE | F24: COUNTRY PERFORMANCE | K24: EXPENSE PERFORMANCE
A26: Row Labels | B26: Sum of Revenue | C26: Sum of Budget Revenue | D26: Sum of Net Profit | F26: Row Labels | G26: Sum of Revenue | H26: Sum of Budget Revenue | I26: Sum of Net Profit | K26: Values
A27: Q1 | B27: 7077127.4 | C27: 7330705.8 | D27: 986863.95 | F27: India | G27: 28075370 | H27: 29125875 | I27: 4049228.1 | K27: Sum of COGS | L27: 16885275
A28: Q2 | B28: 6701298.5 | C28: 6943536.7 | D28: 943235.8 | F28: Grand Total | G28: 28075370 | H28: 29125875 | I28: 4049228.1 | K28: Sum of Operating Expense | L28: 2553433.5
A29: Q3 | B29: 7601780.3 | C29: 7923154 | D29: 1108600.5 | K29: Sum of Marketing Expense | L29: 1601652.6
A30: Q4 | B30: 6695163.9 | C30: 6928478.2 | D30: 1010527.8 | K30: Sum of Salary Expense | L30: 2240126.7
A31: Grand Total | B31: 28075370 | C31: 29125875 | D31: 4049228.1 | K31: Sum of Misc Expense | L31: 745654.55
A33: CLEAN CITY PERFORMANCE | F33: PRODUCT PERFORMANCE
A35: Row Labels | B35: Sum of Revenue | C35: Sum of Net Profit | F35: Row Labels | G35: Sum of Revenue | H35: Sum of Net Profit
A36: Gurugram | B36: 1096211.2 | C36: 143596.18 | F36: Document Scanner | G36: 2452090 | H36: 402031.39
A37: Kanpur | B37: 978053.82 | C37: 136858.6 | F37: UPS System | G37: 2426113.9 | H37: 329561.61
A38: Udaipur | B38: 855967.33 | C38: 131106.79 | F38: Conference Camera | G38: 2339747.2 | H38: 352156.89
A39: Mumbai | B39: 853076.31 | C39: 115741 | F39: Projector | G39: 2203534.8 | H39: 332435.91
A40: Lucknow | B40: 786348.88 | C40: 134202.02 | F40: Monitor | G40: 2193240.1 | H40: 300414.71
A41: Pune | B41: 782884.14 | C41: 120635.84 | F41: Smartphone | G41: 2111913.1 | H41: 305953.15
A42: Jodhpur | B42: 730504.05 | C42: 115241.63 | F42: Printer | G42: 2045797 | H42: 294715.27
A43: Agra | B43: 727010.74 | C43: 93191.51 | F43: Business Laptop | G43: 1944377.2 | H43: 289724.32
A44: Jamshedpur | B44: 709481.63 | C44: 124107.79 | F44: Tablet | G44: 1831477.7 | H44: 213179.73
A45: Bhubaneswar | B45: 706502.21 | C45: 100040.25 | F45: Network Switch | G45: 1273809.8 | H45: 173377.79
A46: Nagpur | B46: 698023.5 | C46: 79222.18 | F46: Network Router | G46: 1197583.1 | H46: 170136.85
A47: Vadodara | B47: 691076.72 | C47: 77209.69 | F47: Office Chair | G47: 1054216.9 | H47: 156411.06
... A56: Coimbatore | B56: 576791.57 | C56: 84002.2 | F56: Grand Total | G56: 28075370 | H56: 4049228.1
A57: Jaipur | B57: 567194.31 | C57: 85026.03
A58: Warangal | B58: 561186.02 | C58: 68502.95
A59: Ahmedabad | B59: 558318.58 | C59: 81221.22
A60: Siliguri | B60: 544903.04 | C60: 89263.82
A61: Nizamabad | B61: 516240.95 | C61: 84095.11
A62: Kochi | B62: 488706.53 | C62: 76737.38
A63: Mysuru | B63: 459639.6 | C63: 76730.98
A64: Kolkata | B64: 452434.68 | C64: 62472.1
A65: Surat | B65: 447465.63 | C65: 59280.19
A66: Panipat | B66: 446496.12 | C66: 59211.71
A67: Cuttack | B67: 445978.69 | C67: 77888.23
A68: Hyderabad | B68: 430559.87 | C68: 74098.44
... A90: Grand Total | B90: 28075370 | C90: 4049228.1

Sheet Dashboard
A1: FINANCIAL PERFORMANCE DASHBOARD
A3: Executive MIS | Revenue • Profitability • Budget • Expense • Regional Performance | FY 2026
A8: TOTAL REVENUE | C8: BUDGET REVENUE | E8: BUDGET ACHIEVEMENT | G8: BUDGET VARIANCE | I8: GROSS PROFIT | K8: NET PROFIT | M8: NET PROFIT MARGIN | O8: TOTAL EXPENSE
A9: =Calculation!C6 -> 28075370 | C9: =Calculation!C7 -> 29125875 | E9: =Calculation!L9 -> 0.96393226 | G9: =Calculation!L8 -> -1050504.6 | I9: =Calculation!C14 -> 11190096 | K9: =Calculation!C15 -> 4049228.1 | M9: =Calculation!F7 -> 0.13343412 | O9: =Calculation!C13 -> 24026142
A40: MANAGEMENT INSIGHTS & BUSINESS ACTION CENTER
A43: REVENUE PERFORMANCE | F43: PROFITABILITY PERFORMANCE | J43: BUDGET PERFORMANCE | N43: EXPENSE STRUCTURE
A44: Actual Revenue | C44: =Calculation!C6 -> 28075370 | F44: Gross Profit | H44: =Calculation!C14 -> 11190096 | J44: Budget Revenue | L44: =Calculation!C7 -> 29125875 | N44: Total Expense | P44: =Calculation!C13 -> 24026142
A45: Budget Revenue | C45: =Calculation!C7 -> 29125875 | F45: Net Profit | H45: =Calculation!C15 -> 4049228.1 | J45: Actual Revenue | L45: =Calculation!C6 -> 28075370 | N45: COGS | P45: =Calculation!C8 -> 16885275
A46: Variance | C46: =C44-C45 -> -1050504.6 | F46: Profit Margin | H46: =Calculation!F7 -> 0.13343412 | J46: Budget Variance | L46: =L45-L44 -> -1050504.6 | N46: Operating Expense | P46: =Calculation!C9 -> 2553433.5
A47: Variance % | C47: =IF(C45=0,0,C46/C45) -> -0.036067743 | F47: Margin Target | H47: =15% -> 0.15 | J47: Achievement % | L47: =IF(L44=0,0,L45/L44) -> 0.96393226 | N47: Expense Ratio | P47: =Calculation!F12 -> 0.85577294
A49: BEST PERFORMING REGION | F49: BEST PERFORMING PRODUCT | J49: BEST PERFORMING MONTH | N49: LOWEST PERFORMING REGION
A50: Region | C50: =INDEX(Calculation!B39:B43,MATCH(MAX(Calculation!C39:C43),Calculation!C39:C43,0)) -> West | F50: Product | G50: =INDEX(Calculation!H22:H41,MATCH(MAX(Calculation!I22:I41),Calculation!I22:I41,0)) -> Document Scanner | J50: Month | K50: =INDEX(Calculation!B22:B33,MATCH(MAX(Calculation!C22:C33),Calculation!C22:C33,0)) -> December | N50: Region | O50: =INDEX(Calculation!B39:B43,MATCH(MIN(Calculation!D39:D43),Calculation!D39:D43,0)) -> Central
A51: Revenue | C51: =MAX(Calculation!C39:C43) -> 8752932.8 | F51: Revenue | G51: =MAX(Calculation!I22:I41) -> 2452090 | J51: Revenue | K51: =MAX(Calculation!C22:C33) -> 2762976.5 | N51: Revenue | O51: =INDEX(Calculation!C39:C43,MATCH(MIN(Calculation!D39:D43),Calculation!D39:D43,0)) -> 3955931.1
A52: Net Profit | C52: =INDEX(Calculation!D39:D43,MATCH(MAX(Calculation!C39:C43),Calculation!C39:C43,0)) -> 1153460.7 | F52: Net Revenue | G52: =INDEX(Calculation!L22:L41,MATCH(MAX(Calculation!I22:I41),Calculation!I22:I41,0)) -> 402031.39 | J52: Net Profit | K52: =INDEX(Calculation!F22:F33,MATCH(MAX(Calculation!C22:C33),Calculation!C22:C33,0)) -> 384284.26 | N52: Net Profit | O52: =MIN(Calculation!D39:D43) -> 528905.52
A53: Profit Margin | C53: =INDEX(Calculation!F39:F43,MATCH(MAX(Calculation!C39:C43),Calculation!C39:C43,0)) -> 0.13177991 | F53: Profit Margin | G53: =INDEX(Calculation!N22:N41,MATCH(MAX(Calculation!I22:I41),Calculation!I22:I41,0)) -> 0.15225278 | J53: Profit Margin | K53: =INDEX(Calculation!F22:F33,MATCH(MAX(Calculation!C22:C33),Calculation!C22:C33,0)) / MAX(Calculation!C22:C33) -> 0.13908343 | N53: Profit Margin | O53: =INDEX(Calculation!F39:F43,MATCH(MIN(Calculation!D39:D43),Calculation!D39:D43,0)) -> 0.13369938
